{
  "recipes": [
    { "id": "old-fashioned", "name": "Old Fashioned", "base": "Whiskey", "method": "Stir", "glass": "Tumbler", "ingredients": [ { "name": "Bourbon Whiskey", "qtyMl": 60 }, { "name": "Sugar Syrup", "qtyMl": 5 }, { "name": "Angostura Bitters", "qtyMl": 1, "label": "2 dashes" } ], "instructions": "Stir ingredients with ice. Strain over fresh ice. Garnish with orange." },
    { "id": "martini", "name": "Dry Martini", "base": "Gin", "method": "Stir", "glass": "Martini", "ingredients": [ { "name": "Gin", "qtyMl": 60 }, { "name": "Dry Vermouth", "qtyMl": 10 } ], "instructions": "Stir with ice. Strain into chilled glass. Garnish with olive." },
    { "id": "daiquiri", "name": "Daiquiri", "base": "Rum", "method": "Shake", "glass": "Coupe", "ingredients": [ { "name": "White Rum", "qtyMl": 60 }, { "name": "Lime Juice", "qtyMl": 30 }, { "name": "Sugar Syrup", "qtyMl": 20 } ], "instructions": "Shake with ice. Fine strain." },
    { "id": "margarita", "name": "Margarita", "base": "Tequila", "method": "Shake", "glass": "Coupe", "ingredients": [ { "name": "Tequila", "qtyMl": 50 }, { "name": "Triple Sec", "qtyMl": 20 }, { "name": "Lime Juice", "qtyMl": 30 } ], "instructions": "Shake with ice. Strain into salt-rimmed glass." },
    { "id": "whisky-sour", "name": "Whisky Sour", "base": "Whiskey", "method": "Shake", "glass": "Tumbler", "ingredients": [ { "name": "Bourbon Whiskey", "qtyMl": 50 }, { "name": "Lemon Juice", "qtyMl": 30 }, { "name": "Sugar Syrup", "qtyMl": 20 }, { "name": "Egg White", "qtyMl": 15, "optional": true } ], "instructions": "Dry shake (no ice) first, then shake with ice. Strain over fresh ice." },
    { "id": "espresso-martini", "name": "Espresso Martini", "base": "Vodka", "method": "Shake", "glass": "Martini", "ingredients": [ { "name": "Vodka", "qtyMl": 40 }, { "name": "Coffee Liqueur", "qtyMl": 20 }, { "name": "Espresso", "qtyMl": 30 }, { "name": "Sugar Syrup", "qtyMl": 5 } ], "instructions": "Shake hard with ice to create foam. Strain into chilled glass." },
    { "id": "negroni", "name": "Negroni", "base": "Gin", "method": "Stir", "glass": "Tumbler", "ingredients": [ { "name": "Gin", "qtyMl": 30 }, { "name": "Campari", "qtyMl": 30 }, { "name": "Sweet Vermouth", "qtyMl": 30 } ], "instructions": "Build in glass over ice. Stir gently. Garnish with orange slice." },
    { "id": "manhattan", "name": "Manhattan", "base": "Whiskey", "method": "Stir", "glass": "Martini", "ingredients": [ { "name": "Rye Whiskey", "qtyMl": 50 }, { "name": "Sweet Vermouth", "qtyMl": 25 }, { "name": "Angostura Bitters", "qtyMl": 1 } ], "instructions": "Stir with ice. Strain into chilled glass. Garnish with cherry." },
    { "id": "mojito", "name": "Mojito", "base": "Rum", "method": "Build", "glass": "Highball", "ingredients": [ { "name": "White Rum", "qtyMl": 50 }, { "name": "Lime Juice", "qtyMl": 25 }, { "name": "Sugar Syrup", "qtyMl": 15 }, { "name": "Mint", "qtyMl": 0 }, { "name": "Soda Water", "qtyMl": 60, "top": true } ], "instructions": "Muddle mint gently. Add ingredients and ice. Top with soda." },
    { "id": "moscow-mule", "name": "Moscow Mule", "base": "Vodka", "method": "Build", "glass": "Mule Mug", "ingredients": [ { "name": "Vodka", "qtyMl": 50 }, { "name": "Lime Juice", "qtyMl": 15 }, { "name": "Ginger Beer", "qtyMl": 100, "top": true } ], "instructions": "Build in mug over ice. Top with Ginger Beer." },
    { "id": "aperol-spritz", "name": "Aperol Spritz", "base": "Wine/Bubbly", "method": "Build", "glass": "Wine Glass", "ingredients": [ { "name": "Prosecco", "qtyMl": 90 }, { "name": "Aperol", "qtyMl": 60 }, { "name": "Soda Water", "qtyMl": 30 } ], "instructions": "Fill glass with ice. Add Prosecco, then Aperol, then Soda." },
    { "id": "bloody-mary", "name": "Bloody Mary", "base": "Vodka", "method": "Roll/Stir", "glass": "Highball", "ingredients": [ { "name": "Vodka", "qtyMl": 45 }, { "name": "Tomato Juice", "qtyMl": 90 }, { "name": "Lemon Juice", "qtyMl": 15 }, { "name": "Worcestershire Sauce", "qtyMl": 2 }, { "name": "Salt", "qtyMl": 0 }, { "name": "Pepper", "qtyMl": 0 } ], "instructions": "Stir gently with ice. Garnish with celery stick." },
    { "id": "cosmopolitan", "name": "Cosmopolitan", "base": "Vodka", "method": "Shake", "glass": "Martini", "ingredients": [ { "name": "Vodka", "qtyMl": 40 }, { "name": "Triple Sec", "qtyMl": 15 }, { "name": "Lime Juice", "qtyMl": 15 }, { "name": "Cranberry Juice", "qtyMl": 30 } ], "instructions": "Shake with ice. Strain into chilled glass." },
    { "id": "tom-collins", "name": "Tom Collins", "base": "Gin", "method": "Shake + top", "glass": "Longdrink", "ingredients": [ { "name": "Gin", "qtyMl": 50 }, { "name": "Lemon Juice", "qtyMl": 30 }, { "name": "Sugar Syrup", "qtyMl": 20 }, { "name": "Soda Water", "qtyMl": 100, "top": true } ], "instructions": "Shake (except soda). Strain onto ice. Top with soda." },
    { "id": "mai-tai", "name": "Mai Tai", "base": "Rum", "method": "Shake", "glass": "Tumbler", "ingredients": [ { "name": "White Rum", "qtyMl": 30 }, { "name": "Dark Rum", "qtyMl": 30 }, { "name": "Triple Sec", "qtyMl": 15 }, { "name": "Orgeat", "qtyMl": 10 }, { "name": "Lime Juice", "qtyMl": 25 } ], "instructions": "Shake hard. Pour unstrained into glass." },
    { "id": "pina-colada", "name": "Piña Colada", "base": "Rum", "method": "Shake/Blend", "glass": "Highball", "ingredients": [ { "name": "White Rum", "qtyMl": 50 }, { "name": "Coconut Cream", "qtyMl": 30 }, { "name": "Pineapple Juice", "qtyMl": 90 } ], "instructions": "Shake hard or blend with crushed ice." },
    { "id": "dark-n-stormy", "name": "Dark 'n' Stormy", "base": "Rum", "method": "Build", "glass": "Highball", "ingredients": [ { "name": "Dark Rum", "qtyMl": 60 }, { "name": "Ginger Beer", "qtyMl": 100 }, { "name": "Lime Juice", "qtyMl": 10 } ], "instructions": "Build in glass over ice. Garnish with lime wedge." },
    { "id": "caipirinha", "name": "Caipirinha", "base": "Cachaça", "method": "Muddle", "glass": "Tumbler", "ingredients": [ { "name": "Cachaça", "qtyMl": 60 }, { "name": "Lime", "qtyMl": 0, "label": "1 whole" }, { "name": "White Cane Sugar", "qtyMl": 0, "label": "2 tsp" } ], "instructions": "Muddle lime chunks and sugar. Add ice and Cachaça. Stir." },
    { "id": "gin-fizz", "name": "Gin Fizz", "base": "Gin", "method": "Shake + top", "glass": "Highball", "ingredients": [ { "name": "Gin", "qtyMl": 50 }, { "name": "Lemon Juice", "qtyMl": 30 }, { "name": "Sugar Syrup", "qtyMl": 10 }, { "name": "Soda Water", "qtyMl": 80, "top": true } ], "instructions": "Shake (no soda). Strain into glass (no ice). Top with soda." },
    { "id": "white-russian", "name": "White Russian", "base": "Vodka", "method": "Build", "glass": "Tumbler", "ingredients": [ { "name": "Vodka", "qtyMl": 50 }, { "name": "Coffee Liqueur", "qtyMl": 20 }, { "name": "Cream", "qtyMl": 30, "float": true } ], "instructions": "Build vodka and liqueur over ice. Float cream on top." },
    { "id": "bellini", "name": "Bellini", "base": "Wine/Bubbly", "method": "Stir", "glass": "Flute", "ingredients": [ { "name": "Prosecco", "qtyMl": 100 }, { "name": "Peach Puree", "qtyMl": 50 } ], "instructions": "Pour puree into glass. Top gently with Prosecco." },
    { "id": "french-75", "name": "French 75", "base": "Gin", "method": "Shake + top", "glass": "Flute", "ingredients": [ { "name": "Gin", "qtyMl": 30 }, { "name": "Lemon Juice", "qtyMl": 15 }, { "name": "Sugar Syrup", "qtyMl": 15 }, { "name": "Sparkling Wine", "qtyMl": 60, "top": true } ], "instructions": "Shake first 3 ingredients. Strain into flute. Top with Champagne." },
    { "id": "gimlet", "name": "Gimlet", "base": "Gin", "method": "Shake", "glass": "Coupe", "ingredients": [ { "name": "Gin", "qtyMl": 60 }, { "name": "Lime Juice", "qtyMl": 30 }, { "name": "Sugar Syrup", "qtyMl": 15 } ], "instructions": "Shake with ice. Strain into chilled glass." },
    { "id": "paloma", "name": "Paloma", "base": "Tequila", "method": "Build", "glass": "Highball", "ingredients": [ { "name": "Tequila", "qtyMl": 50 }, { "name": "Lime Juice", "qtyMl": 10 }, { "name": "Grapefruit Soda", "qtyMl": 100, "top": true } ], "instructions": "Build in glass with ice. Stir." },
    { "id": "mint-julep", "name": "Mint Julep", "base": "Whiskey", "method": "Muddle", "glass": "Julep Cup", "ingredients": [ { "name": "Bourbon Whiskey", "qtyMl": 60 }, { "name": "Mint", "qtyMl": 0 }, { "name": "Sugar Syrup", "qtyMl": 10 } ], "instructions": "Muddle mint gently. Fill cup with crushed ice. Add bourbon. Stir until cup frosts." },
    { "id": "tequila-sunrise", "name": "Tequila Sunrise", "base": "Tequila", "method": "Build", "glass": "Highball", "ingredients": [ { "name": "Tequila", "qtyMl": 50 }, { "name": "Orange Juice", "qtyMl": 100 }, { "name": "Grenadine", "qtyMl": 10, "float": true } ], "instructions": "Build tequila and juice. Sink grenadine to bottom." },
    { "id": "long-island", "name": "Long Island Iced Tea", "base": "Vodka", "method": "Build", "glass": "Highball", "ingredients": [ { "name": "Vodka", "qtyMl": 15 }, { "name": "Rum", "qtyMl": 15 }, { "name": "Gin", "qtyMl": 15 }, { "name": "Tequila", "qtyMl": 15 }, { "name": "Triple Sec", "qtyMl": 15 }, { "name": "Lemon Juice", "qtyMl": 25 }, { "name": "Sugar Syrup", "qtyMl": 15 }, { "name": "Cola", "qtyMl": 40, "top": true } ], "instructions": "Shake all spirits/sour. Strain into ice-filled glass. Top with Cola." },
    { "id": "cuba-libre", "name": "Cuba Libre", "base": "Rum", "method": "Build", "glass": "Highball", "ingredients": [ { "name": "Aged Rum", "qtyMl": 50 }, { "name": "Lime Juice", "qtyMl": 10 }, { "name": "Cola", "qtyMl": 120, "top": true } ], "instructions": "Build in glass over ice. Garnish with lime wedge." },
    { "id": "shirley-temple", "name": "Shirley Temple", "base": "Non-Alcoholic", "method": "Build", "glass": "Highball", "ingredients": [ { "name": "Ginger Ale", "qtyMl": 100 }, { "name": "Grenadine", "qtyMl": 20 }, { "name": "Lemon Juice", "qtyMl": 5 } ], "instructions": "Build over ice. Garnish with cherry." },
    { "id": "virgin-colada", "name": "Virgin Colada", "base": "Non-Alcoholic", "method": "Blend/Shake", "glass": "Highball", "ingredients": [ { "name": "Pineapple Juice", "qtyMl": 120 }, { "name": "Coconut Cream", "qtyMl": 40 }, { "name": "Cream", "qtyMl": 20 } ], "instructions": "Shake hard or blend with crushed ice." },
    { "id": "americano", "name": "Americano", "base": "Liqueur", "method": "Build", "glass": "Tumbler", "ingredients": [ { "name": "Campari", "qtyMl": 40 }, { "name": "Sweet Vermouth", "qtyMl": 40 }, { "name": "Soda Water", "qtyMl": 60, "top": true } ], "instructions": "Build in glass over ice. Garnish with orange slice." },
    { "id": "bronx", "name": "Bronx", "base": "Gin", "method": "Shake", "glass": "Martini", "ingredients": [ { "name": "Gin", "qtyMl": 30 }, { "name": "Dry Vermouth", "qtyMl": 15 }, { "name": "Sweet Vermouth", "qtyMl": 15 }, { "name": "Orange Juice", "qtyMl": 30 } ], "instructions": "Shake with ice. Strain into chilled glass." },
    { "id": "bamboo", "name": "Bamboo", "base": "Wine/Bubbly", "method": "Stir", "glass": "Martini", "ingredients": [ { "name": "Sherry", "qtyMl": 40 }, { "name": "Dry Vermouth", "qtyMl": 20 }, { "name": "Angostura Bitters", "qtyMl": 1, "label": "2 dashes" } ], "instructions": "Stir with ice. Strain into chilled glass." },
    { "id": "sherry-flip", "name": "Sherry Flip", "base": "Wine/Bubbly", "method": "Shake", "glass": "Flute", "ingredients": [ { "name": "Sherry", "qtyMl": 40 }, { "name": "Brandy", "qtyMl": 10 }, { "name": "Sugar Syrup", "qtyMl": 10 }, { "name": "Cream", "qtyMl": 20 }, { "name": "Egg Yolk", "qtyMl": 20, "label": "1 yolk" } ], "instructions": "Shake hard with ice. Strain. Garnish with nutmeg." },
    { "id": "champagne-cocktail", "name": "Champagne Cocktail", "base": "Wine/Bubbly", "method": "Build", "glass": "Flute", "ingredients": [ { "name": "Champagne", "qtyMl": 100 }, { "name": "Sugar", "qtyMl": 0, "label": "1 cube" }, { "name": "Angostura Bitters", "qtyMl": 1, "label": "2 dashes" } ], "instructions": "Soak sugar cube in bitters. Drop into flute. Top with Champagne." },
    { "id": "black-velvet", "name": "Black Velvet", "base": "Wine/Bubbly", "method": "Build", "glass": "Flute", "ingredients": [ { "name": "Champagne", "qtyMl": 60 }, { "name": "Guinness", "qtyMl": 60 } ], "instructions": "Fill half with Champagne, top with Guinness." },
    { "id": "prince-of-wales", "name": "Prince of Wales", "base": "Wine/Bubbly", "method": "Build", "glass": "Flute", "ingredients": [ { "name": "Cognac", "qtyMl": 20 }, { "name": "Triple Sec", "qtyMl": 10 }, { "name": "Angostura Bitters", "qtyMl": 1 }, { "name": "Champagne", "qtyMl": 90, "top": true } ], "instructions": "Build in glass (or silver cup). Top with Champagne." },
    { "id": "pick-me-up", "name": "Pick Me Up", "base": "Wine/Bubbly", "method": "Shake + top", "glass": "Flute", "ingredients": [ { "name": "Cognac", "qtyMl": 40 }, { "name": "Lemon Juice", "qtyMl": 20 }, { "name": "Grenadine", "qtyMl": 10 }, { "name": "Champagne", "qtyMl": 90, "top": true } ], "instructions": "Shake (except Champagne). Strain into flute. Top with Champagne." },
    { "id": "white-lady", "name": "White Lady", "base": "Gin", "method": "Shake", "glass": "Coupe", "ingredients": [ { "name": "Gin", "qtyMl": 40 }, { "name": "Triple Sec", "qtyMl": 20 }, { "name": "Lemon Juice", "qtyMl": 20 } ], "instructions": "Shake with ice. Strain into chilled glass." },
    { "id": "paradise", "name": "Paradise", "base": "Gin", "method": "Shake", "glass": "Coupe", "ingredients": [ { "name": "Gin", "qtyMl": 40 }, { "name": "Apricot Brandy", "qtyMl": 20 }, { "name": "Orange Juice", "qtyMl": 40 } ], "instructions": "Shake with ice. Strain into chilled glass." },
    { "id": "pink-lady", "name": "Pink Lady", "base": "Gin", "method": "Shake", "glass": "Coupe", "ingredients": [ { "name": "Gin", "qtyMl": 40 }, { "name": "Lemon Juice", "qtyMl": 15 }, { "name": "Grenadine", "qtyMl": 15 }, { "name": "Egg White", "qtyMl": 15, "optional": true } ], "instructions": "Shake hard with ice. Strain into chilled glass." },
    { "id": "gin-alexander", "name": "Gin Alexander", "base": "Gin", "method": "Shake", "glass": "Coupe", "ingredients": [ { "name": "Gin", "qtyMl": 40 }, { "name": "White Crème de Cacao", "qtyMl": 20 }, { "name": "Cream", "qtyMl": 40 } ], "instructions": "Shake with ice. Strain. Garnish with nutmeg." },
    { "id": "sloe-gin-fizz", "name": "Sloe Gin Fizz", "base": "Gin", "method": "Shake + top", "glass": "Highball", "ingredients": [ { "name": "Sloe Gin", "qtyMl": 50 }, { "name": "Lemon Juice", "qtyMl": 30 }, { "name": "Sugar Syrup", "qtyMl": 20 }, { "name": "Soda Water", "qtyMl": 80, "top": true } ], "instructions": "Shake (except soda). Strain into glass. Top with soda." },
    { "id": "pink-sling", "name": "Pink Sling", "base": "Gin", "method": "Shake", "glass": "Highball", "ingredients": [ { "name": "Gin", "qtyMl": 40 }, { "name": "Crème de Cassis", "qtyMl": 20 }, { "name": "Grenadine", "qtyMl": 10 }, { "name": "Lemon Juice", "qtyMl": 20 }, { "name": "Pineapple Juice", "qtyMl": 100 } ], "instructions": "Shake with ice. Strain into ice-filled glass." },
    { "id": "red-lion", "name": "Red Lion", "base": "Gin", "method": "Shake", "glass": "Martini", "ingredients": [ { "name": "Gin", "qtyMl": 30 }, { "name": "Grand Marnier", "qtyMl": 20 }, { "name": "Lemon Juice", "qtyMl": 10 }, { "name": "Orange Juice", "qtyMl": 40 } ], "instructions": "Shake with ice. Strain into chilled glass." },
    { "id": "harvey-wallbanger", "name": "Harvey Wallbanger", "base": "Vodka", "method": "Build", "glass": "Highball", "ingredients": [ { "name": "Vodka", "qtyMl": 40 }, { "name": "Orange Juice", "qtyMl": 100 }, { "name": "Galliano", "qtyMl": 10, "float": true } ], "instructions": "Build vodka and juice over ice. Float Galliano on top." },
    { "id": "swimming-pool", "name": "Swimming Pool", "base": "Vodka", "method": "Blend/Shake", "glass": "Highball", "ingredients": [ { "name": "Vodka", "qtyMl": 40 }, { "name": "Blue Curaçao", "qtyMl": 20 }, { "name": "Pineapple Juice", "qtyMl": 120 }, { "name": "Coconut Cream", "qtyMl": 20 }, { "name": "Cream", "qtyMl": 20 } ], "instructions": "Shake hard or blend. Pour into glass over crushed ice." },
    { "id": "blue-lagoon", "name": "Blue Lagoon", "base": "Vodka", "method": "Build", "glass": "Highball", "ingredients": [ { "name": "Vodka", "qtyMl": 40 }, { "name": "Blue Curaçao", "qtyMl": 20 }, { "name": "Lemon Juice", "qtyMl": 10 }, { "name": "Ginger Ale", "qtyMl": 100, "top": true } ], "instructions": "Build in glass over ice. Top with Ginger Ale or Lemonade." },
    { "id": "salty-dog", "name": "Salty Dog", "base": "Vodka", "method": "Build", "glass": "Highball", "ingredients": [ { "name": "Vodka", "qtyMl": 50 }, { "name": "Grapefruit Juice", "qtyMl": 100 }, { "name": "Salt", "qtyMl": 0, "label": "Rim" } ], "instructions": "Rim glass with salt. Build ingredients over ice." },
    { "id": "screwdriver", "name": "Screwdriver", "base": "Vodka", "method": "Build", "glass": "Highball", "ingredients": [ { "name": "Vodka", "qtyMl": 50 }, { "name": "Orange Juice", "qtyMl": 120 } ], "instructions": "Build in glass over ice." },
    { "id": "chi-chi", "name": "Chi-Chi", "base": "Vodka", "method": "Blend", "glass": "Highball", "ingredients": [ { "name": "Vodka", "qtyMl": 60 }, { "name": "Pineapple Juice", "qtyMl": 80 }, { "name": "Coconut Cream", "qtyMl": 40 }, { "name": "Cream", "qtyMl": 20 } ], "instructions": "Blend with crushed ice." },
    { "id": "el-presidente", "name": "El Presidente", "base": "Rum", "method": "Stir", "glass": "Coupe", "ingredients": [ { "name": "White Rum", "qtyMl": 40 }, { "name": "Dry Vermouth", "qtyMl": 20 }, { "name": "Triple Sec", "qtyMl": 10 }, { "name": "Grenadine", "qtyMl": 5 } ], "instructions": "Stir with ice. Strain into chilled glass." },
    { "id": "scorpion", "name": "Scorpion", "base": "Rum", "method": "Shake", "glass": "Highball", "ingredients": [ { "name": "White Rum", "qtyMl": 60 }, { "name": "Brandy", "qtyMl": 20 }, { "name": "Orange Juice", "qtyMl": 80 }, { "name": "Lemon Juice", "qtyMl": 20 }, { "name": "Orgeat", "qtyMl": 20 } ], "instructions": "Shake with ice. Pour into large glass." },
    { "id": "zombie", "name": "Zombie", "base": "Rum", "method": "Shake", "glass": "Highball", "ingredients": [ { "name": "White Rum", "qtyMl": 40 }, { "name": "Dark Rum", "qtyMl": 40 }, { "name": "Triple Sec", "qtyMl": 20 }, { "name": "Grenadine", "qtyMl": 20 }, { "name": "Lemon Juice", "qtyMl": 40 }, { "name": "Orange Juice", "qtyMl": 40 }, { "name": "Pineapple Juice", "qtyMl": 40 } ], "instructions": "Shake hard with ice. Pour unstrained into large glass." },
    { "id": "blue-hawaii", "name": "Blue Hawaii", "base": "Rum", "method": "Shake", "glass": "Coupe", "ingredients": [ { "name": "White Rum", "qtyMl": 20 }, { "name": "Triple Sec", "qtyMl": 20 }, { "name": "Blue Curaçao", "qtyMl": 20 }, { "name": "Cream", "qtyMl": 40 } ], "instructions": "Shake with ice. Strain into chilled glass." },
    { "id": "rum-alexander", "name": "Rum Alexander", "base": "Rum", "method": "Shake", "glass": "Coupe", "ingredients": [ { "name": "Dark Rum", "qtyMl": 40 }, { "name": "Brown Crème de Cacao", "qtyMl": 20 }, { "name": "Cream", "qtyMl": 40 } ], "instructions": "Shake with ice. Strain. Garnish with nutmeg." },
    { "id": "el-diabolo", "name": "El Diabolo", "base": "Tequila", "method": "Build", "glass": "Highball", "ingredients": [ { "name": "Tequila", "qtyMl": 50 }, { "name": "Crème de Cassis", "qtyMl": 20 }, { "name": "Lime Juice", "qtyMl": 10, "label": "Wedge" }, { "name": "Ginger Ale", "qtyMl": 100, "top": true } ], "instructions": "Build over ice. Squeeze lime wedge. Top with Ginger Ale." },
    { "id": "mexican-sunset", "name": "Mexican Sunset", "base": "Tequila", "method": "Shake", "glass": "Tumbler", "ingredients": [ { "name": "Tequila", "qtyMl": 30 }, { "name": "Triple Sec", "qtyMl": 20 }, { "name": "Orange Juice", "qtyMl": 30 }, { "name": "Lemon Juice", "qtyMl": 10 }, { "name": "Orgeat", "qtyMl": 10 } ], "instructions": "Shake with ice. Strain over fresh ice." },
    { "id": "b-and-b", "name": "B and B", "base": "Brandy", "method": "Build", "glass": "Tumbler", "ingredients": [ { "name": "Bénédictine", "qtyMl": 20 }, { "name": "Cognac", "qtyMl": 20 } ], "instructions": "Build in glass (or snifter). No ice." },
    { "id": "between-the-sheets", "name": "Between the Sheets", "base": "Brandy", "method": "Shake", "glass": "Coupe", "ingredients": [ { "name": "Cognac", "qtyMl": 20 }, { "name": "White Rum", "qtyMl": 20 }, { "name": "Triple Sec", "qtyMl": 20 }, { "name": "Lemon Juice", "qtyMl": 10 } ], "instructions": "Shake with ice. Strain into chilled glass." },
    { "id": "brandy-alexander", "name": "Brandy Alexander", "base": "Brandy", "method": "Shake", "glass": "Coupe", "ingredients": [ { "name": "Brandy", "qtyMl": 40 }, { "name": "Brown Crème de Cacao", "qtyMl": 20 }, { "name": "Cream", "qtyMl": 40 } ], "instructions": "Shake with ice. Strain. Garnish with nutmeg." },
    { "id": "sidecar", "name": "Sidecar", "base": "Brandy", "method": "Shake", "glass": "Coupe", "ingredients": [ { "name": "Brandy", "qtyMl": 40 }, { "name": "Triple Sec", "qtyMl": 20 }, { "name": "Lemon Juice", "qtyMl": 20 } ], "instructions": "Shake with ice. Strain into sugar-rimmed glass." },
    { "id": "brandy-eggnog", "name": "Brandy Eggnog", "base": "Brandy", "method": "Shake", "glass": "Highball", "ingredients": [ { "name": "Brandy", "qtyMl": 60 }, { "name": "Sugar Syrup", "qtyMl": 10 }, { "name": "Egg Yolk", "qtyMl": 20, "label": "1 yolk" }, { "name": "Milk", "qtyMl": 120 }, { "name": "Cream", "qtyMl": 20 } ], "instructions": "Shake hard with ice. Strain into glass. Garnish with nutmeg." },
    { "id": "jack-rose", "name": "Jack Rose", "base": "Calvados", "method": "Shake", "glass": "Coupe", "ingredients": [ { "name": "Calvados", "qtyMl": 40 }, { "name": "Lemon Juice", "qtyMl": 20 }, { "name": "Grenadine", "qtyMl": 10 } ], "instructions": "Shake with ice. Strain into chilled glass." },
    { "id": "pisco-sour", "name": "Pisco Sour", "base": "Pisco", "method": "Shake", "glass": "Tumbler", "ingredients": [ { "name": "Pisco", "qtyMl": 50 }, { "name": "Sugar Syrup", "qtyMl": 20 }, { "name": "Lime Juice", "qtyMl": 20 }, { "name": "Egg White", "qtyMl": 15 }, { "name": "Angostura Bitters", "qtyMl": 1, "label": "Dash" } ], "instructions": "Shake hard with ice. Strain. Top with bitters." },
    { "id": "porto-flip", "name": "Porto Flip", "base": "Wine/Bubbly", "method": "Shake", "glass": "Flute", "ingredients": [ { "name": "Port", "qtyMl": 40 }, { "name": "Cognac", "qtyMl": 10 }, { "name": "Sugar Syrup", "qtyMl": 10 }, { "name": "Cream", "qtyMl": 20 }, { "name": "Egg Yolk", "qtyMl": 20 } ], "instructions": "Shake hard with ice. Strain. Garnish with nutmeg." },
    { "id": "a-and-a-ginger-ale", "name": "A & A Ginger Ale", "base": "Liqueur", "method": "Build", "glass": "Highball", "ingredients": [ { "name": "A & A Riesling Liqueur", "qtyMl": 40 }, { "name": "Ginger Ale", "qtyMl": 100, "top": true } ], "instructions": "Pour liqueur into a glass with ice. Top with cold Ginger Ale. Garnish with white grapes." },
    { "id": "adria-look", "name": "Adria Look", "base": "Wine/Bubbly", "method": "Shake + top", "glass": "Flute", "ingredients": [ { "name": "Blue Curaçao", "qtyMl": 20 }, { "name": "Gin", "qtyMl": 20 }, { "name": "Lemon Juice", "qtyMl": 20 }, { "name": "Sparkling Wine", "qtyMl": 80, "top": true } ], "instructions": "Shake ingredients (except Sparkling Wine) with ice. Strain into a large glass. Top with Sparkling Wine. Garnish with apricot and cherry." },
    { "id": "adonis", "name": "Adonis", "base": "Sherry", "method": "Stir", "glass": "Cocktail", "ingredients": [ { "name": "Fino Sherry", "qtyMl": 40 }, { "name": "Sweet Vermouth", "qtyMl": 20 }, { "name": "Orange Bitters", "qtyMl": 1, "label": "2 dashes" } ], "instructions": "Stir with ice. Strain into a chilled glass. Garnish with lemon twist." },
    { "id": "after-all", "name": "After All", "base": "Calvados", "method": "Shake", "glass": "Cocktail", "ingredients": [ { "name": "Calvados", "qtyMl": 40 }, { "name": "Peach Liqueur", "qtyMl": 30 }, { "name": "Lemon Juice", "qtyMl": 20 } ], "instructions": "Shake well with ice. Strain into a cocktail glass." },
    { "id": "alfonso", "name": "Alfonso", "base": "Wine/Bubbly", "method": "Build", "glass": "Flute", "ingredients": [ { "name": "Champagne", "qtyMl": 100 }, { "name": "Dubonnet Rouge", "qtyMl": 40 }, { "name": "Sugar", "qtyMl": 0, "label": "1 cube" }, { "name": "Angostura Bitters", "qtyMl": 1, "label": "2 dashes" } ], "instructions": "Soak sugar cube in bitters in the glass. Add Dubonnet and one ice cube. Top with Champagne. Garnish with lemon twist." },
    { "id": "alligator", "name": "Alligator", "base": "Spirit", "method": "Shake", "glass": "Highball", "ingredients": [ { "name": "Pastis", "qtyMl": 20 }, { "name": "Blue Curaçao", "qtyMl": 20 }, { "name": "Passion Fruit Nectar", "qtyMl": 120 }, { "name": "Angostura Bitters", "qtyMl": 1, "label": "1 dash" } ], "instructions": "Shake vigorously with ice. Strain into a glass with fresh ice. Garnish with lemon slice and cherry." },
    { "id": "american-beauty", "name": "American Beauty", "base": "Brandy", "method": "Shake", "glass": "Tumbler", "ingredients": [ { "name": "Cognac", "qtyMl": 20 }, { "name": "Dry Vermouth", "qtyMl": 20 }, { "name": "Grenadine", "qtyMl": 10 }, { "name": "Orange Juice", "qtyMl": 20 }, { "name": "White Crème de Menthe", "qtyMl": 1, "label": "1 dash" }, { "name": "Port", "qtyMl": 5, "float": true } ], "instructions": "Shake (except Port) with ice. Strain into glass with ice. Float Port on top." },
    { "id": "americano", "name": "Americano", "base": "Liqueur", "method": "Build", "glass": "Tumbler", "ingredients": [ { "name": "Campari", "qtyMl": 40 }, { "name": "Sweet Vermouth", "qtyMl": 40 }, { "name": "Soda Water", "qtyMl": 60, "top": true } ], "instructions": "Build in glass over ice. Garnish with orange slice or lemon twist." },
    { "id": "andalusia-cooler", "name": "Andalusia Cooler", "base": "Sherry", "method": "Shake + top", "glass": "Highball", "ingredients": [ { "name": "Cream Sherry", "qtyMl": 50 }, { "name": "Cherry Brandy", "qtyMl": 20 }, { "name": "Orange Juice", "qtyMl": 50 }, { "name": "Lemon Juice", "qtyMl": 10 }, { "name": "Bitter Lemon", "qtyMl": 80, "top": true } ], "instructions": "Shake (except Bitter Lemon) with ice. Strain into glass with ice. Top with Bitter Lemon." },
    { "id": "aperol-spritz-a", "name": "Aperol Spritz", "base": "Wine/Bubbly", "method": "Build", "glass": "Wine Glass", "ingredients": [ { "name": "Prosecco", "qtyMl": 90 }, { "name": "Aperol", "qtyMl": 60 }, { "name": "Soda Water", "qtyMl": 30 } ], "instructions": "Fill glass with ice. Add Prosecco, then Aperol, then Soda. Garnish with orange slice." },
    { "id": "apple-bang", "name": "Apple Bang", "base": "Calvados", "method": "Build", "glass": "Highball", "ingredients": [ { "name": "Calvados", "qtyMl": 60 }, { "name": "Cider", "qtyMl": 120, "top": true } ], "instructions": "Pour Calvados over ice. Top with cold Cider. Garnish with apple wedge." },
    { "id": "apple-scotch", "name": "Apple Scotch", "base": "Whiskey", "method": "Shake", "glass": "Tumbler", "ingredients": [ { "name": "Calvados", "qtyMl": 40 }, { "name": "Scotch Whisky", "qtyMl": 20 }, { "name": "Lemon Juice", "qtyMl": 30 }, { "name": "Sugar Syrup", "qtyMl": 20 } ], "instructions": "Shake well with ice. Strain into glass with ice. Garnish with lemon slice and cherry." },
    { "id": "applecart", "name": "Applecart", "base": "Calvados", "method": "Shake", "glass": "Cocktail", "ingredients": [ { "name": "Calvados", "qtyMl": 40 }, { "name": "Cointreau", "qtyMl": 20 }, { "name": "Lemon Juice", "qtyMl": 20 } ], "instructions": "Shake well with ice. Strain into a cocktail glass." },
    { "id": "applejack", "name": "Applejack", "base": "Calvados", "method": "Shake", "glass": "Cocktail", "ingredients": [ { "name": "Calvados", "qtyMl": 30 }, { "name": "Dry Orange Curaçao", "qtyMl": 20 }, { "name": "Lemon Juice", "qtyMl": 20 } ], "instructions": "Shake well with ice. Strain into a cocktail glass." },
    { "id": "applejack-flip", "name": "Applejack Flip", "base": "Calvados", "method": "Shake", "glass": "Flute", "ingredients": [ { "name": "Calvados", "qtyMl": 50 }, { "name": "Sugar Syrup", "qtyMl": 10 }, { "name": "Cream", "qtyMl": 20 }, { "name": "Egg Yolk", "qtyMl": 20, "label": "1 yolk" } ], "instructions": "Shake vigorously with ice. Strain. Dust with nutmeg." },
    { "id": "applejack-highball", "name": "Applejack Highball", "base": "Calvados", "method": "Build", "glass": "Highball", "ingredients": [ { "name": "Calvados", "qtyMl": 60 }, { "name": "Ginger Ale", "qtyMl": 120, "top": true } ], "instructions": "Pour Calvados over ice. Top with Ginger Ale. Garnish with apple peel." },
    { "id": "applejack-punch", "name": "Applejack Punch", "base": "Calvados", "method": "Build", "glass": "Highball", "ingredients": [ { "name": "Calvados", "qtyMl": 40 }, { "name": "Orange Juice", "qtyMl": 40 }, { "name": "Grenadine", "qtyMl": 10 }, { "name": "Ginger Ale", "qtyMl": 100, "top": true } ], "instructions": "Build in glass with ice. Stir well. Top with Ginger Ale." },
    { "id": "apps-with-pears", "name": "Apps with Pears", "base": "Calvados", "method": "Shake", "glass": "Cocktail", "ingredients": [ { "name": "Calvados", "qtyMl": 20 }, { "name": "Pear Brandy", "qtyMl": 20 }, { "name": "Peach Liqueur", "qtyMl": 10 }, { "name": "Apple Juice", "qtyMl": 40, "label": "Cloudy" }, { "name": "Lime Juice", "qtyMl": 5 } ], "instructions": "Shake with ice. Strain into chilled glass. Garnish with apple and pear slices." },
    { "id": "apricot-secco", "name": "Apricot Secco", "base": "Gin", "method": "Stir", "glass": "Cocktail", "ingredients": [ { "name": "Gin", "qtyMl": 20 }, { "name": "Dry Vermouth", "qtyMl": 20 }, { "name": "Apricot Brandy", "qtyMl": 20 } ], "instructions": "Stir with ice in a mixing glass. Strain into chilled cocktail glass." },
    { "id": "arranco", "name": "Arranco", "base": "Cachaça", "method": "Shake", "glass": "Tumbler", "ingredients": [ { "name": "Cachaça", "qtyMl": 40 }, { "name": "Cherry Brandy", "qtyMl": 20 }, { "name": "Lemon Juice", "qtyMl": 20 }, { "name": "Orange Juice", "qtyMl": 60 } ], "instructions": "Shake well with ice. Strain into a large tumbler with fresh ice. Garnish with strawberry." },
    { "id": "azzurro-bacio", "name": "Azzurro Bacio", "base": "Wine/Bubbly", "method": "Shake + top", "glass": "Flute", "ingredients": [ { "name": "Blue Curaçao", "qtyMl": 30 }, { "name": "Lime Syrup", "qtyMl": 20 }, { "name": "Lemon Juice", "qtyMl": 10 }, { "name": "Sparkling Wine", "qtyMl": 100, "top": true } ], "instructions": "Shake (except Sparkling Wine) with ice. Strain into large glass. Top with Sparkling Wine." },
    { "id": "bahama-mama", "name": "Bahama Mama", "base": "Rum", "method": "Shake", "glass": "Highball", "ingredients": [ { "name": "Aged Rum", "qtyMl": 20 }, { "name": "Overproof Rum", "qtyMl": 10 }, { "name": "Coconut Liqueur", "qtyMl": 20 }, { "name": "Coffee Liqueur", "qtyMl": 10 }, { "name": "Pineapple Juice", "qtyMl": 120 }, { "name": "Lemon Juice", "qtyMl": 20 } ], "instructions": "Shake with ice. Strain into a highball glass with ice. Garnish with star fruit and cherry." },
    { "id": "bamboo", "name": "Bamboo", "base": "Sherry", "method": "Stir", "glass": "Martini", "ingredients": [ { "name": "Fino Sherry", "qtyMl": 40 }, { "name": "Dry Vermouth", "qtyMl": 20 }, { "name": "Orange Bitters", "qtyMl": 1, "label": "2 dashes" } ], "instructions": "Stir with ice. Strain into a chilled glass." },
    { "id": "banana-boat", "name": "Banana Boat", "base": "Gin", "method": "Shake", "glass": "Fancy", "ingredients": [ { "name": "Gin", "qtyMl": 30 }, { "name": "Crème de Bananes", "qtyMl": 30 }, { "name": "Orange Juice", "qtyMl": 120 }, { "name": "Grenadine", "qtyMl": 1, "label": "Dash" } ], "instructions": "Shake with ice. Strain into a large fancy glass with ice. Drizzle Grenadine on top. Garnish with orange slice and cherry." },
    { "id": "banana-royal", "name": "Banana Royal", "base": "Rum", "method": "Blend", "glass": "Fancy", "ingredients": [ { "name": "Banana", "qtyMl": 0, "label": "1/2" }, { "name": "Aged Rum", "qtyMl": 50 }, { "name": "Pineapple Juice", "qtyMl": 80 }, { "name": "Cream", "qtyMl": 20 }, { "name": "Coconut Cream", "qtyMl": 20 } ], "instructions": "Blend with ice. Pour into a fancy glass with ice. Garnish with fruits." },
    { "id": "barbara", "name": "Barbara", "base": "Vodka", "method": "Shake", "glass": "Coupe", "ingredients": [ { "name": "Vodka", "qtyMl": 40 }, { "name": "Brown Crème de Cacao", "qtyMl": 20 }, { "name": "Cream", "qtyMl": 40 } ], "instructions": "Shake with ice. Strain into a cocktail glass." },
    { "id": "batida-banana", "name": "Batida Banana", "base": "Cachaça", "method": "Blend", "glass": "Tumbler", "ingredients": [ { "name": "Cachaça", "qtyMl": 40 }, { "name": "Crème de Bananes", "qtyMl": 10 }, { "name": "Lemon Juice", "qtyMl": 20 }, { "name": "Banana", "qtyMl": 0, "label": "1 whole" } ], "instructions": "Blend with ice. Pour into a glass over crushed ice. Garnish with banana slices." },
    { "id": "batida-de-abacaxi", "name": "Batida de Abacaxi", "base": "Cachaça", "method": "Build", "glass": "Tumbler", "ingredients": [ { "name": "Lime", "qtyMl": 0, "label": "1 whole" }, { "name": "Cachaça", "qtyMl": 60 }, { "name": "Pineapple Juice", "qtyMl": 40 }, { "name": "Sugar Syrup", "qtyMl": 5 } ], "instructions": "Quarter lime and squeeze into glass. Add lime pieces, syrup, juice, and Cachaça. Stir well with ice." },
    { "id": "batida-de-maracuja", "name": "Batida de Maracuja con Limão", "base": "Cachaça", "method": "Build", "glass": "Tumbler", "ingredients": [ { "name": "Lime", "qtyMl": 0, "label": "1 whole" }, { "name": "Cachaça", "qtyMl": 60 }, { "name": "Passion Fruit Nectar", "qtyMl": 40 } ], "instructions": "Quarter lime and squeeze into glass. Add lime pieces, Cachaça, and nectar. Stir with ice." },
    { "id": "batida-de-mel", "name": "Batida de Mel", "base": "Cachaça", "method": "Build", "glass": "Tumbler", "ingredients": [ { "name": "Lime", "qtyMl": 0, "label": "2 whole" }, { "name": "Cachaça", "qtyMl": 60 }, { "name": "Lime Juice", "qtyMl": 60 }, { "name": "Honey", "qtyMl": 5 } ], "instructions": "Squeeze limes into glass. Add pieces, Cachaça, and Lime Juice. Stir. Drizzle honey on top." },
    { "id": "beach-beauty", "name": "Beach Beauty", "base": "Vodka", "method": "Shake + top", "glass": "Fancy", "ingredients": [ { "name": "Vodka", "qtyMl": 40 }, { "name": "Crème de Bananes", "qtyMl": 20 }, { "name": "Grenadine", "qtyMl": 10 }, { "name": "Orange Juice", "qtyMl": 40 }, { "name": "Tonic Water", "qtyMl": 100, "top": true } ], "instructions": "Shake (except Tonic) with ice. Strain into glass with ice. Top with Tonic. Garnish with orange." },
    { "id": "bel-air", "name": "Bel Air", "base": "Gin", "method": "Stir", "glass": "Cocktail", "ingredients": [ { "name": "Gin", "qtyMl": 40 }, { "name": "Sweet Vermouth", "qtyMl": 20 }, { "name": "Blue Curaçao", "qtyMl": 10 } ], "instructions": "Stir with ice. Strain into a chilled glass. Garnish with orange zest." },
    { "id": "bentley", "name": "Bentley", "base": "Calvados", "method": "Stir", "glass": "Cocktail", "ingredients": [ { "name": "Dubonnet Rouge", "qtyMl": 30 }, { "name": "Calvados", "qtyMl": 30 } ], "instructions": "Stir with ice. Strain into a chilled cocktail glass." },
    { "id": "berry-rosso", "name": "Berry Rosso", "base": "Vermouth", "method": "Shake", "glass": "Highball", "ingredients": [ { "name": "Sweet Vermouth", "qtyMl": 30 }, { "name": "Vodka", "qtyMl": 20 }, { "name": "Strawberry Syrup", "qtyMl": 10 }, { "name": "Lemon Juice", "qtyMl": 20 }, { "name": "Orange Juice", "qtyMl": 80 } ], "instructions": "Shake with ice. Strain into a glass with crushed ice. Garnish with a strawberry." },
    { "id": "betsy-rose", "name": "Betsy Rose", "base": "Cognac", "method": "Stir", "glass": "Cocktail", "ingredients": [ { "name": "Cognac", "qtyMl": 30 }, { "name": "Port", "qtyMl": 30 }, { "name": "Blue Curaçao", "qtyMl": 10 }, { "name": "Angostura Bitters", "qtyMl": 1, "label": "Dash" } ], "instructions": "Stir with ice. Strain into a chilled glass. Express orange zest over drink." },
    { "id": "betsy-ross", "name": "Betsy Ross", "base": "Brandy", "method": "Stir", "glass": "Cocktail", "ingredients": [ { "name": "Brandy", "qtyMl": 30 }, { "name": "Port", "qtyMl": 30 }, { "name": "Cointreau", "qtyMl": 5 }, { "name": "Angostura Bitters", "qtyMl": 1, "label": "Dash" } ], "instructions": "Stir with ice. Strain into a chilled glass." },
    { "id": "betty-blue", "name": "Betty Blue", "base": "Vodka", "method": "Stir", "glass": "Cocktail", "ingredients": [ { "name": "Vodka", "qtyMl": 40 }, { "name": "Dry Vermouth", "qtyMl": 20 }, { "name": "Peach Liqueur", "qtyMl": 10 }, { "name": "Blue Curaçao", "qtyMl": 1, "label": "Dash" } ], "instructions": "Stir with ice. Strain into a chilled glass. Express orange zest over drink." },
    { "id": "big-apple", "name": "Big Apple", "base": "Calvados", "method": "Stir", "glass": "Cocktail", "ingredients": [ { "name": "Calvados", "qtyMl": 20 }, { "name": "Dry Vermouth", "qtyMl": 30 }, { "name": "Peach Liqueur", "qtyMl": 20 } ], "instructions": "Stir with ice. Strain into a chilled glass. Garnish with a mini apple." },
    { "id": "big-ben", "name": "Big Ben", "base": "Gin", "method": "Shake + top", "glass": "Highball", "ingredients": [ { "name": "Gin", "qtyMl": 50 }, { "name": "Lemon Juice", "qtyMl": 20 }, { "name": "Orange Juice", "qtyMl": 40 }, { "name": "Grenadine", "qtyMl": 10 }, { "name": "Bitter Lemon", "qtyMl": 100, "top": true } ], "instructions": "Shake (except Bitter Lemon) with ice. Strain into a glass with ice. Top with Bitter Lemon." },
    { "id": "bitter-pastis", "name": "Bitter Pastis", "base": "Anise", "method": "Build", "glass": "Highball", "ingredients": [ { "name": "Pastis", "qtyMl": 30 }, { "name": "Vodka", "qtyMl": 30 }, { "name": "Lemon Juice", "qtyMl": 30 }, { "name": "Bitter Lemon", "qtyMl": 100, "top": true } ], "instructions": "Add Pastis, Vodka, and juice to a glass with ice. Stir. Top with Bitter Lemon." },
    { "id": "bitter-orange", "name": "Bitter-Orange", "base": "Aperitif", "method": "Build", "glass": "Highball", "ingredients": [ { "name": "Campari", "qtyMl": 40 }, { "name": "Orange Juice", "qtyMl": 120 } ], "instructions": "Pour Campari into a glass with ice. Top with Orange Juice. Garnish with orange slice." },
    { "id": "black-magic", "name": "Black Magic", "base": "Wine/Bubbly", "method": "Build", "glass": "Flute", "ingredients": [ { "name": "Cherry Juice", "qtyMl": 60 }, { "name": "Triple Sec", "qtyMl": 20 }, { "name": "Sparkling Wine", "qtyMl": 100, "top": true } ], "instructions": "Pour juice and Triple Sec into a flute. Top with Sparkling Wine." },
    { "id": "bloody-bull", "name": "Bloody Bull", "base": "Vodka", "method": "Build", "glass": "Highball", "ingredients": [ { "name": "Vodka", "qtyMl": 50 }, { "name": "Tomato Juice", "qtyMl": 60 }, { "name": "Consommé", "qtyMl": 60 }, { "name": "Lemon Juice", "qtyMl": 1, "label": "Dash" }, { "name": "Tabasco", "qtyMl": 1, "label": "Splash" }, { "name": "Worcestershire Sauce", "qtyMl": 1, "label": "Splash" } ], "instructions": "Build in a glass with ice. Stir well. Garnish with lemon slice." },
    { "id": "blow-up", "name": "Blow Up", "base": "Wine/Bubbly", "method": "Shake + top", "glass": "Highball", "ingredients": [ { "name": "Strawberry Syrup", "qtyMl": 20 }, { "name": "Triple Sec", "qtyMl": 20 }, { "name": "Orange Juice", "qtyMl": 60 }, { "name": "Sparkling Wine", "qtyMl": 100, "top": true } ], "instructions": "Shake (except Sparkling Wine) with ice. Strain into a glass with ice. Top with Sparkling Wine." },
    { "id": "blue-dream", "name": "Blue Dream", "base": "Vodka", "method": "Build", "glass": "Highball", "ingredients": [ { "name": "Vodka", "qtyMl": 60 }, { "name": "Orange Juice", "qtyMl": 120 }, { "name": "Blue Curaçao", "qtyMl": 20, "float": true } ], "instructions": "Pour Vodka and juice into a glass with ice. Float Blue Curaçao on top." },
    { "id": "blue-lady", "name": "Blue Lady", "base": "Gin", "method": "Shake", "glass": "Coupe", "ingredients": [ { "name": "Gin", "qtyMl": 40 }, { "name": "Blue Curaçao", "qtyMl": 20 }, { "name": "Lemon Juice", "qtyMl": 20 } ], "instructions": "Shake with ice. Strain into a cocktail glass." },
    { "id": "blue-wind", "name": "Blue Wind", "base": "Anise", "method": "Shake + top", "glass": "Highball", "ingredients": [ { "name": "Anisette", "qtyMl": 20 }, { "name": "Gin", "qtyMl": 20 }, { "name": "Blue Curaçao", "qtyMl": 10 }, { "name": "Lemon Juice", "qtyMl": 10 }, { "name": "Tonic Water", "qtyMl": 100, "top": true } ], "instructions": "Shake (except Tonic) with ice. Strain into a glass with ice. Top with Tonic." },
    { "id": "brandy-collins", "name": "Brandy Collins", "base": "Brandy", "method": "Shake + top", "glass": "Highball", "ingredients": [ { "name": "Brandy", "qtyMl": 50 }, { "name": "Lemon Juice", "qtyMl": 30 }, { "name": "Sugar Syrup", "qtyMl": 20 }, { "name": "Soda Water", "qtyMl": 100, "top": true } ], "instructions": "Shake (except Soda) with ice. Strain into a glass with ice. Top with Soda." },
    { "id": "brandy-fino", "name": "Brandy Fino", "base": "Sherry", "method": "Stir", "glass": "Cocktail", "ingredients": [ { "name": "Fino Sherry", "qtyMl": 20 }, { "name": "Cognac", "qtyMl": 20 }, { "name": "Drambuie", "qtyMl": 20 } ], "instructions": "Stir with ice. Strain into a chilled glass. Express lemon zest over drink." },
    { "id": "brandy-fizz", "name": "Brandy Fizz", "base": "Brandy", "method": "Shake + top", "glass": "Highball", "ingredients": [ { "name": "Cognac", "qtyMl": 50 }, { "name": "Lemon Juice", "qtyMl": 30 }, { "name": "Sugar Syrup", "qtyMl": 20 }, { "name": "Soda Water", "qtyMl": 80, "top": true } ], "instructions": "Shake (except Soda) with ice. Strain into a glass (no ice). Top with Soda." },
    { "id": "brandy-flip", "name": "Brandy Flip", "base": "Brandy", "method": "Shake", "glass": "Coupe", "ingredients": [ { "name": "Cognac", "qtyMl": 50 }, { "name": "Sugar Syrup", "qtyMl": 10 }, { "name": "Cream", "qtyMl": 20 }, { "name": "Egg Yolk", "qtyMl": 20, "label": "1 yolk" } ], "instructions": "Shake vigorously with ice. Strain. Dust with nutmeg." },
    { "id": "brandy-sour", "name": "Brandy Sour", "base": "Brandy", "method": "Shake", "glass": "Tumbler", "ingredients": [ { "name": "Cognac", "qtyMl": 50 }, { "name": "Lemon Juice", "qtyMl": 30 }, { "name": "Sugar Syrup", "qtyMl": 20 } ], "instructions": "Shake with ice. Strain into a glass. Garnish with orange and cherry." },
    { "id": "bueno-vista", "name": "Bueno Vista", "base": "Rum", "method": "Stir", "glass": "Cocktail", "ingredients": [ { "name": "Aged Rum", "qtyMl": 20 }, { "name": "Dry Vermouth", "qtyMl": 20 }, { "name": "Peach Liqueur", "qtyMl": 10 }, { "name": "Port", "qtyMl": 20 }, { "name": "Grenadine", "qtyMl": 10 } ], "instructions": "Stir with ice. Strain into a chilled glass. Express orange zest over drink." },
    { "id": "bull-shot", "name": "Bull Shot", "base": "Vodka", "method": "Build", "glass": "Highball", "ingredients": [ { "name": "Vodka", "qtyMl": 50 }, { "name": "Lemon Juice", "qtyMl": 10 }, { "name": "Consommé", "qtyMl": 120 }, { "name": "Worcestershire Sauce", "qtyMl": 1, "label": "Splash" }, { "name": "Tabasco", "qtyMl": 1, "label": "Splash" }, { "name": "Pepper", "qtyMl": 0 } ], "instructions": "Build in a glass with ice. Stir well." },
    { "id": "cachaca-berry", "name": "Cachaça Berry", "base": "Cachaça", "method": "Shake", "glass": "Tumbler", "ingredients": [ { "name": "Cachaça", "qtyMl": 30 }, { "name": "Raspberry Liqueur", "qtyMl": 30 }, { "name": "White Wine", "qtyMl": 30 }, { "name": "Blackberries", "qtyMl": 0, "label": "3" }, { "name": "Raspberries", "qtyMl": 0, "label": "3" } ], "instructions": "Muddle berries in glass with crushed ice. Shake liquids with ice and strain into the glass. Garnish with berries." },
    { "id": "cachaca-laranja", "name": "Cachaça Laranja", "base": "Cachaça", "method": "Build", "glass": "Longdrink", "ingredients": [ { "name": "Cachaça", "qtyMl": 60 }, { "name": "Orange Juice", "qtyMl": 120 } ], "instructions": "Pour into a glass with ice. Stir briefly. Garnish with orange slice." },
    { "id": "cachaca-maracuja", "name": "Cachaça Maracuja", "base": "Cachaça", "method": "Build", "glass": "Longdrink", "ingredients": [ { "name": "Cachaça", "qtyMl": 50 }, { "name": "Passion Fruit Nectar", "qtyMl": 120 } ], "instructions": "Pour into a glass with ice. Stir briefly. Garnish with orange slice." },
    { "id": "caipirinha-limao", "name": "Caipirinha Limão", "base": "Cachaça", "method": "Muddle", "glass": "Tumbler", "ingredients": [ { "name": "Cachaça", "qtyMl": 60 }, { "name": "Lime Syrup", "qtyMl": 20 }, { "name": "Pineapple Juice", "qtyMl": 80 }, { "name": "Lime", "qtyMl": 0, "label": "2 wedges" } ], "instructions": "Squeeze limes into glass. Add ingredients. Stir with crushed ice. Garnish with pineapple." },
    { "id": "caipirovka", "name": "Caipirovka", "base": "Vodka", "method": "Muddle", "glass": "Tumbler", "ingredients": [ { "name": "Vodka", "qtyMl": 60 }, { "name": "Sugar Syrup", "qtyMl": 20 }, { "name": "Lime", "qtyMl": 0, "label": "1-2 whole" } ], "instructions": "Muddle lime quarters in glass. Add Vodka and syrup. Fill with crushed ice and stir." },
    { "id": "calvados-cocktail", "name": "Calvados Cocktail", "base": "Calvados", "method": "Shake", "glass": "Coupe", "ingredients": [ { "name": "Calvados", "qtyMl": 40 }, { "name": "Cointreau", "qtyMl": 10 }, { "name": "Orange Juice", "qtyMl": 40 }, { "name": "Peach Liqueur", "qtyMl": 10 } ], "instructions": "Shake with ice. Strain into a cocktail glass. Garnish with apple piece." },
    { "id": "calvados-sour", "name": "Calvados Sour", "base": "Calvados", "method": "Shake", "glass": "Cocktail", "ingredients": [ { "name": "Calvados", "qtyMl": 50 }, { "name": "Lemon Juice", "qtyMl": 30 }, { "name": "Sugar Syrup", "qtyMl": 20 } ], "instructions": "Shake vigorously with ice. Strain. Garnish with orange and cherry." },
    { "id": "canarian", "name": "Canarian", "base": "Spirit", "method": "Shake", "glass": "Longdrink", "ingredients": [ { "name": "Raki", "qtyMl": 40 }, { "name": "Maraschino", "qtyMl": 20 }, { "name": "Grenadine", "qtyMl": 10 }, { "name": "Orange Juice", "qtyMl": 80 }, { "name": "Lemon Juice", "qtyMl": 20 } ], "instructions": "Shake with ice. Strain into a glass with ice. Garnish with orange and cherry." },
    { "id": "caribbean", "name": "Caribbean", "base": "Rum", "method": "Shake + top", "glass": "Longdrink", "ingredients": [ { "name": "White Rum", "qtyMl": 20 }, { "name": "Crème de Bananes", "qtyMl": 20 }, { "name": "Banana Nectar", "qtyMl": 40 }, { "name": "Sparkling Wine", "qtyMl": 100, "top": true } ], "instructions": "Shake (except Sparkling Wine) with ice. Strain into a glass with ice. Top with Sparkling Wine. Garnish with Kiwi." },
    { "id": "caribbean-champagne", "name": "Caribbean Champagne", "base": "Wine/Bubbly", "method": "Build", "glass": "Flute", "ingredients": [ { "name": "Champagne", "qtyMl": 100 }, { "name": "White Rum", "qtyMl": 10 }, { "name": "Crème de Bananes", "qtyMl": 10 }, { "name": "Angostura Bitters", "qtyMl": 1, "label": "1 dash" } ], "instructions": "Add ingredients to glass with one ice cube. Top with Champagne. Garnish with banana." },
    { "id": "caribbean-mule", "name": "Caribbean Mule", "base": "Rum", "method": "Shake + top", "glass": "Mule Mug", "ingredients": [ { "name": "Spiced Rum", "qtyMl": 60 }, { "name": "Sugar Syrup", "qtyMl": 20 }, { "name": "Lime Juice", "qtyMl": 20 }, { "name": "Ginger Beer", "qtyMl": 100, "top": true } ], "instructions": "Shake (except Ginger Beer) with ice. Strain into mug with ice. Top with Ginger Beer." },
    { "id": "caribbean-shake", "name": "Caribbean Shake", "base": "Rum", "method": "Shake", "glass": "Longdrink", "ingredients": [ { "name": "Aged Rum", "qtyMl": 40 }, { "name": "Vanilla Syrup", "qtyMl": 10 }, { "name": "Mango Syrup", "qtyMl": 15 }, { "name": "Coconut Liqueur", "qtyMl": 15 }, { "name": "Passion Fruit Nectar", "qtyMl": 100 } ], "instructions": "Shake with ice. Strain into a glass with ice. Garnish with Mango." },
    { "id": "champagne-cocktail-ii", "name": "Champagne Cocktail II", "base": "Wine/Bubbly", "method": "Stir", "glass": "Flute", "ingredients": [ { "name": "Champagne", "qtyMl": 100 }, { "name": "Cointreau", "qtyMl": 20 }, { "name": "Cognac", "qtyMl": 20 } ], "instructions": "Stir Cointreau and Cognac with ice. Strain into glass. Top with Champagne. Garnish with orange and cherry." },
    { "id": "champagne-flip", "name": "Champagne Flip", "base": "Wine/Bubbly", "method": "Shake + top", "glass": "Flute", "ingredients": [ { "name": "Cognac", "qtyMl": 10 }, { "name": "White Wine", "qtyMl": 40 }, { "name": "Sugar Syrup", "qtyMl": 10 }, { "name": "Cream", "qtyMl": 20 }, { "name": "Egg Yolk", "qtyMl": 20, "label": "1 yolk" }, { "name": "Champagne", "qtyMl": 50, "top": true } ], "instructions": "Shake (except Champagne) vigorously with ice. Strain into glass. Top with Champagne. Dust with nutmeg." },
    { "id": "citrus-rum-cooler", "name": "Citrus Rum Cooler", "base": "Rum", "method": "Shake + top", "glass": "Longdrink", "ingredients": [ { "name": "Aged Rum", "qtyMl": 40 }, { "name": "Melon Liqueur", "qtyMl": 20 }, { "name": "Orange Juice", "qtyMl": 60 }, { "name": "Lemonade", "qtyMl": 80, "top": true } ], "instructions": "Shake (except Lemonade) with ice. Strain into glass with ice. Top with Lemonade." },
    { "id": "city-life", "name": "City Life", "base": "Tequila", "method": "Shake", "glass": "Tumbler", "ingredients": [ { "name": "Tequila", "qtyMl": 10 }, { "name": "Cointreau", "qtyMl": 20 }, { "name": "Passion Fruit Liqueur", "qtyMl": 20 }, { "name": "Grapefruit Juice", "qtyMl": 50 } ], "instructions": "Shake with ice. Strain into glass with crushed ice. Garnish with lime slice." },
    { "id": "claridge", "name": "Claridge", "base": "Gin", "method": "Stir", "glass": "Cocktail", "ingredients": [ { "name": "Gin", "qtyMl": 20 }, { "name": "Dry Vermouth", "qtyMl": 20 }, { "name": "Cointreau", "qtyMl": 10 }, { "name": "Apricot Brandy", "qtyMl": 10 } ], "instructions": "Stir with ice. Strain into chilled glass." },
    { "id": "costa-de-la-luz", "name": "Costa de la Luz", "base": "Rum", "method": "Shake", "glass": "Longdrink", "ingredients": [ { "name": "White Rum", "qtyMl": 40 }, { "name": "Grenadine", "qtyMl": 10 }, { "name": "Mango Syrup", "qtyMl": 10 }, { "name": "Lemon Juice", "qtyMl": 30 }, { "name": "Orange Juice", "qtyMl": 100 } ], "instructions": "Shake with ice. Strain into glass with ice. Garnish with pineapple." },
    { "id": "cranberry-punch", "name": "Cranberry Punch", "base": "Vodka", "method": "Shake", "glass": "Longdrink", "ingredients": [ { "name": "Vodka", "qtyMl": 40 }, { "name": "Grenadine", "qtyMl": 20 }, { "name": "Lemon Juice", "qtyMl": 10 }, { "name": "Orange Juice", "qtyMl": 40 }, { "name": "Cranberry Juice", "qtyMl": 100 } ], "instructions": "Shake with ice. Strain into glass with ice. Garnish with orange." },
    { "id": "creamy-orange", "name": "Creamy Orange", "base": "Sherry", "method": "Shake", "glass": "Coupe", "ingredients": [ { "name": "Cream Sherry", "qtyMl": 40 }, { "name": "Cognac", "qtyMl": 10 }, { "name": "Orange Juice", "qtyMl": 40 }, { "name": "Cream", "qtyMl": 20 } ], "instructions": "Shake with ice. Strain into a cocktail glass." },
    { "id": "crushed-power", "name": "Crushed Power", "base": "Gin", "method": "Muddle", "glass": "Tumbler", "ingredients": [ { "name": "Gin", "qtyMl": 50 }, { "name": "Kumquats", "qtyMl": 0, "label": "4" }, { "name": "Lime", "qtyMl": 0, "label": "1/4" }, { "name": "Brown Sugar", "qtyMl": 0, "label": "2 tsp" }, { "name": "Lime Juice Cordial", "qtyMl": 20 } ], "instructions": "Muddle fruits with sugar. Add liquids. Fill with crushed ice and stir." },
    { "id": "crystal-waters", "name": "Crystal Waters", "base": "Vodka", "method": "Shake + top", "glass": "Longdrink", "ingredients": [ { "name": "Orange Vodka", "qtyMl": 25 }, { "name": "Vanilla Vodka", "qtyMl": 25 }, { "name": "Peach Liqueur", "qtyMl": 10 }, { "name": "Lime Juice Cordial", "qtyMl": 10 }, { "name": "Lime Juice", "qtyMl": 20 }, { "name": "Lemonade", "qtyMl": 120, "top": true } ], "instructions": "Shake (except Lemonade) with ice. Strain into glass with ice. Top with Lemonade." },
    { "id": "cognac-summit", "name": "Cognac Summit", "base": "Cognac", "method": "Build", "glass": "Tumbler", "ingredients": [ { "name": "Cognac", "qtyMl": 40 }, { "name": "Ginger", "qtyMl": 0, "label": "4 slices" }, { "name": "Lime", "qtyMl": 0, "label": "1 zest" }, { "name": "Lemonade", "qtyMl": 60, "top": true }, { "name": "Cucumber", "qtyMl": 0, "label": "1 slice" } ], "instructions": "Muddle ginger and lime zest in glass. Add ice and Cognac. Top with Lemonade. Garnish with cucumber slice." },
    { "id": "daiquiri-blossom", "name": "Daiquiri Blossom", "base": "Rum", "method": "Shake", "glass": "Coupe", "ingredients": [ { "name": "White Rum", "qtyMl": 40 }, { "name": "Maraschino", "qtyMl": 20 }, { "name": "Orange Juice", "qtyMl": 20 } ], "instructions": "Shake with ice. Strain into a chilled cocktail glass. Garnish with a cocktail cherry." },
    { "id": "daiquiri-on-the-rocks", "name": "Daiquiri on the rocks", "base": "Rum", "method": "Shake", "glass": "Tumbler", "ingredients": [ { "name": "White Rum", "qtyMl": 50 }, { "name": "Sugar Syrup", "qtyMl": 20 }, { "name": "Lime Juice", "qtyMl": 30 } ], "instructions": "Shake vigorously with ice. Strain into a tumbler over ice cubes." },
    { "id": "dandy", "name": "Dandy", "base": "Whiskey", "method": "Stir", "glass": "Cocktail", "ingredients": [ { "name": "Rye Whiskey", "qtyMl": 30 }, { "name": "Dubonnet Rouge", "qtyMl": 30 }, { "name": "Cointreau", "qtyMl": 10 }, { "name": "Angostura Bitters", "qtyMl": 1, "label": "Dash" } ], "instructions": "Stir with ice. Strain into a chilled cocktail glass. Express orange zest over drink." },
    { "id": "danziger-kutscher", "name": "Danziger Kutscher", "base": "Spirit", "method": "Shake", "glass": "Tumbler", "ingredients": [ { "name": "Goldwasser", "qtyMl": 40 }, { "name": "Vodka", "qtyMl": 20 }, { "name": "Apricot Brandy", "qtyMl": 10 }, { "name": "Lime Juice", "qtyMl": 10 } ], "instructions": "Shake with ice. Strain into a tumbler over crushed ice. Garnish with lime slice." },
    { "id": "dark-n-stormy", "name": "Dark 'n' Stormy", "base": "Rum", "method": "Build", "glass": "Highball", "ingredients": [ { "name": "Dark Rum", "qtyMl": 60 }, { "name": "Ginger Beer", "qtyMl": 100, "top": true }, { "name": "Lime Juice", "qtyMl": 10 } ], "instructions": "Pour rum and lime juice into a glass with ice. Top with Ginger Beer. Garnish with a lime wedge." },
    { "id": "deauville", "name": "Deauville", "base": "Brandy", "method": "Shake", "glass": "Cocktail", "ingredients": [ { "name": "Cognac", "qtyMl": 20 }, { "name": "Calvados", "qtyMl": 20 }, { "name": "Cointreau", "qtyMl": 20 }, { "name": "Lemon Juice", "qtyMl": 20 } ], "instructions": "Shake with ice. Strain into a cocktail glass. Garnish with lemon twist." },
    { "id": "deborah", "name": "Deborah", "base": "Tequila", "method": "Shake", "glass": "Cocktail", "ingredients": [ { "name": "Tequila", "qtyMl": 30 }, { "name": "White Rum", "qtyMl": 10 }, { "name": "Galliano", "qtyMl": 10 }, { "name": "Orange Juice", "qtyMl": 40 }, { "name": "Lime Juice", "qtyMl": 10 } ], "instructions": "Shake with ice. Strain into a chilled cocktail glass. Garnish with orange zest." },
    { "id": "deep-purple", "name": "Deep Purple", "base": "Liqueur", "method": "Shake + top", "glass": "Highball", "ingredients": [ { "name": "Blue Curaçao", "qtyMl": 30 }, { "name": "Passion Fruit Nectar", "qtyMl": 60 }, { "name": "Bitter Lemon", "qtyMl": 100, "top": true }, { "name": "Grenadine", "qtyMl": 10, "float": true } ], "instructions": "Shake Curaçao and nectar with ice. Strain into glass with ice. Top with Bitter Lemon. Float Grenadine on top." },
    { "id": "derby", "name": "Derby", "base": "Gin", "method": "Stir", "glass": "Cocktail", "ingredients": [ { "name": "Gin", "qtyMl": 50 }, { "name": "Peach Bitters", "qtyMl": 1, "label": "2 dashes" }, { "name": "Mint", "qtyMl": 0, "label": "2 leaves" } ], "instructions": "Stir with ice. Strain into a chilled cocktail glass. Garnish with mint leaf." },
    { "id": "derby-daiquiri", "name": "Derby Daiquiri", "base": "Rum", "method": "Blend", "glass": "Coupe", "ingredients": [ { "name": "White Rum", "qtyMl": 40 }, { "name": "Orange Juice", "qtyMl": 20 }, { "name": "Lime Juice", "qtyMl": 10 }, { "name": "Sugar Syrup", "qtyMl": 10 } ], "instructions": "Blend with crushed ice. Pour into a chilled cocktail glass (do not strain)." },
    { "id": "derby-fizz", "name": "Derby Fizz", "base": "Whiskey", "method": "Shake + top", "glass": "Highball", "ingredients": [ { "name": "Scotch Whisky", "qtyMl": 40 }, { "name": "Orange Juice", "qtyMl": 20 }, { "name": "Lemon Juice", "qtyMl": 20 }, { "name": "Sugar Syrup", "qtyMl": 10 }, { "name": "Soda Water", "qtyMl": 80, "top": true }, { "name": "Egg", "qtyMl": 0, "label": "1 whole" } ], "instructions": "Shake (except Soda) vigorously with ice. Strain into glass (no ice). Top with Soda." },
    { "id": "desert-healer", "name": "Desert Healer", "base": "Gin", "method": "Shake + top", "glass": "Highball", "ingredients": [ { "name": "Gin", "qtyMl": 20 }, { "name": "Cherry Brandy", "qtyMl": 20 }, { "name": "Orange Juice", "qtyMl": 100 }, { "name": "Ginger Ale", "qtyMl": 40, "top": true } ], "instructions": "Shake (except Ginger Ale) with ice. Strain into glass with ice. Top with Ginger Ale. Garnish with orange and cherry." },
    { "id": "diabolo", "name": "Diabolo", "base": "Rum", "method": "Stir", "glass": "Cocktail", "ingredients": [ { "name": "White Rum", "qtyMl": 40 }, { "name": "Dry Vermouth", "qtyMl": 10 }, { "name": "Cointreau", "qtyMl": 10 }, { "name": "Angostura Bitters", "qtyMl": 1, "label": "Dash" } ], "instructions": "Stir with ice. Strain into a chilled cocktail glass. Garnish with orange zest." },
    { "id": "dirty-mother", "name": "Dirty Mother", "base": "Brandy", "method": "Build", "glass": "Tumbler", "ingredients": [ { "name": "Brandy", "qtyMl": 40 }, { "name": "Coffee Liqueur", "qtyMl": 20 } ], "instructions": "Build in a tumbler over ice. Stir gently." },
    { "id": "dizzy-izzy", "name": "Dizzy Izzy", "base": "Sherry", "method": "Shake", "glass": "Fancy", "ingredients": [ { "name": "Cream Sherry", "qtyMl": 30 }, { "name": "Bourbon Whiskey", "qtyMl": 30 }, { "name": "Pineapple Juice", "qtyMl": 20 }, { "name": "Lemon Juice", "qtyMl": 20 } ], "instructions": "Shake with ice. Strain into a fancy glass. Garnish with pineapple." },
    { "id": "domino", "name": "Domino", "base": "Gin", "method": "Build", "glass": "Tumbler", "ingredients": [ { "name": "Gin", "qtyMl": 30 }, { "name": "Dry Vermouth", "qtyMl": 30 }, { "name": "Dubonnet Rouge", "qtyMl": 30 } ], "instructions": "Pour ingredients into a tumbler over ice. Stir well. Garnish with lemon twist." },
    { "id": "dr-funk", "name": "Dr. Funk", "base": "Rum", "method": "Shake", "glass": "Highball", "ingredients": [ { "name": "Dark Rum", "qtyMl": 40 }, { "name": "Pernod", "qtyMl": 1, "label": "Dash" }, { "name": "Lemon Juice", "qtyMl": 20 }, { "name": "Grenadine", "qtyMl": 10 }, { "name": "Soda Water", "qtyMl": 40 } ], "instructions": "Shake (except Soda) with ice. Strain into glass with ice. Top with Soda." },
    { "id": "dream-cocktail", "name": "Dream Cocktail", "base": "Brandy", "method": "Shake", "glass": "Cocktail", "ingredients": [ { "name": "Brandy", "qtyMl": 40 }, { "name": "Cointreau", "qtyMl": 20 }, { "name": "Pernod", "qtyMl": 1, "label": "Dash" } ], "instructions": "Shake with ice. Strain into a chilled cocktail glass." },
    { "id": "dreams-cocktail", "name": "Dream's Cocktail", "base": "Wine/Bubbly", "method": "Shake + top", "glass": "Coupe", "ingredients": [ { "name": "Dubonnet Rouge", "qtyMl": 20 }, { "name": "Cointreau", "qtyMl": 20 }, { "name": "Grapefruit Juice", "qtyMl": 20 }, { "name": "Champagne", "qtyMl": 60, "top": true } ], "instructions": "Shake (except Champagne) with ice. Strain into glass. Top with Champagne." },
    { "id": "drivers-long-island-ice-tea", "name": "Driver's Long Island Ice Tea", "base": "Non-Alcoholic", "method": "Build", "glass": "Highball", "ingredients": [ { "name": "Lemon Juice", "qtyMl": 20 }, { "name": "Sugar Syrup", "qtyMl": 20 }, { "name": "Cold Black Tea", "qtyMl": 80 }, { "name": "Cola", "qtyMl": 80, "top": true } ], "instructions": "Build in glass over ice. Top with Cola. Garnish with lemon slice." },
    { "id": "drivers-margarita", "name": "Driver's Margarita", "base": "Non-Alcoholic", "method": "Shake", "glass": "Coupe", "ingredients": [ { "name": "Lime Juice", "qtyMl": 40 }, { "name": "Lemon Juice", "qtyMl": 20 }, { "name": "Sugar Syrup", "qtyMl": 20 }, { "name": "Orange Juice", "qtyMl": 20 } ], "instructions": "Shake with ice. Strain into salt-rimmed glass. Garnish with lime slice." },
    { "id": "dubonnet-cocktail", "name": "Dubonnet Cocktail", "base": "Aperitif", "method": "Stir", "glass": "Cocktail", "ingredients": [ { "name": "Dubonnet Rouge", "qtyMl": 40 }, { "name": "Gin", "qtyMl": 20 }, { "name": "Orange Bitters", "qtyMl": 1, "label": "Dash" } ], "instructions": "Stir with ice. Strain into a chilled cocktail glass. Garnish with lemon twist." },
    { "id": "dubonnet-fizz", "name": "Dubonnet Fizz", "base": "Aperitif", "method": "Shake + top", "glass": "Highball", "ingredients": [ { "name": "Dubonnet Rouge", "qtyMl": 50 }, { "name": "Cherry Brandy", "qtyMl": 10 }, { "name": "Lemon Juice", "qtyMl": 20 }, { "name": "Orange Juice", "qtyMl": 40 }, { "name": "Soda Water", "qtyMl": 60, "top": true } ], "instructions": "Shake (except Soda) with ice. Strain into glass with ice. Top with Soda. Garnish with orange slice." },
    { "id": "duchess", "name": "Duchess", "base": "Vermouth", "method": "Stir", "glass": "Cocktail", "ingredients": [ { "name": "Dry Vermouth", "qtyMl": 20 }, { "name": "Sweet Vermouth", "qtyMl": 20 }, { "name": "Absinthe", "qtyMl": 20 } ], "instructions": "Stir with ice. Strain into a chilled cocktail glass." },
    { "id": "duke", "name": "Duke", "base": "Wine/Bubbly", "method": "Shake + top", "glass": "Flute", "ingredients": [ { "name": "Cointreau", "qtyMl": 20 }, { "name": "Maraschino", "qtyMl": 10 }, { "name": "Orange Juice", "qtyMl": 20 }, { "name": "Lime Juice", "qtyMl": 20 }, { "name": "Champagne", "qtyMl": 80, "top": true } ], "instructions": "Shake (except Champagne) with ice. Strain into glass. Top with Champagne. Garnish with orange spiral." },
    { "id": "duke-of-marlborough", "name": "Duke of Marlborough", "base": "Sherry", "method": "Shake", "glass": "Coupe", "ingredients": [ { "name": "Fino Sherry", "qtyMl": 30 }, { "name": "Sweet Vermouth", "qtyMl": 30 }, { "name": "Lemon Juice", "qtyMl": 30 }, { "name": "Grenadine", "qtyMl": 10 } ], "instructions": "Shake with ice. Strain into a chilled cocktail glass." },
    { "id": "dutch-trade", "name": "Dutch Trade", "base": "Gin", "method": "Shake", "glass": "Cocktail", "ingredients": [ { "name": "Genever", "qtyMl": 40 }, { "name": "Curacao Orange", "qtyMl": 20 }, { "name": "Lemon Juice", "qtyMl": 20 } ], "instructions": "Shake with ice. Strain into a chilled cocktail glass." },
    { "id": "eagles-dream", "name": "Eagle's Dream", "base": "Gin", "method": "Shake", "glass": "Coupe", "ingredients": [ { "name": "Gin", "qtyMl": 40 }, { "name": "Creme de Violette", "qtyMl": 20 }, { "name": "Lemon Juice", "qtyMl": 20 }, { "name": "Egg White", "qtyMl": 15 }, { "name": "Sugar Syrup", "qtyMl": 5 } ], "instructions": "Shake hard with ice. Strain into a chilled cocktail glass." },
    { "id": "earthquake", "name": "Earthquake", "base": "Spirit", "method": "Shake", "glass": "Coupe", "ingredients": [ { "name": "Gin", "qtyMl": 30 }, { "name": "Whiskey", "qtyMl": 30 }, { "name": "Absinthe", "qtyMl": 30 } ], "instructions": "Shake with ice. Strain into a chilled glass. (Very strong!)" },
    { "id": "east-india", "name": "East India", "base": "Brandy", "method": "Stir", "glass": "Cocktail", "ingredients": [ { "name": "Brandy", "qtyMl": 50 }, { "name": "Pineapple Juice", "qtyMl": 10 }, { "name": "Dry Orange Curaçao", "qtyMl": 10 }, { "name": "Maraschino", "qtyMl": 5 }, { "name": "Angostura Bitters", "qtyMl": 1, "label": "Dash" } ], "instructions": "Stir with ice. Strain into a chilled glass. Garnish with a cherry." },
    { "id": "easter-bunny", "name": "Easter Bunny", "base": "Vodka", "method": "Shake", "glass": "Cocktail", "ingredients": [ { "name": "Vodka", "qtyMl": 40 }, { "name": "Chocolate Liqueur", "qtyMl": 20 }, { "name": "Cherry Brandy", "qtyMl": 10 }, { "name": "Lemon Juice", "qtyMl": 10 } ], "instructions": "Shake with ice. Strain into a chilled glass." },
    { "id": "eden", "name": "Eden", "base": "Gin", "method": "Stir", "glass": "Cocktail", "ingredients": [ { "name": "Gin", "qtyMl": 40 }, { "name": "Sweet Vermouth", "qtyMl": 30 }, { "name": "Apricot Brandy", "qtyMl": 20 }, { "name": "Lime Juice", "qtyMl": 10 } ], "instructions": "Stir with ice. Strain into a chilled glass." },
    { "id": "egg-nog", "name": "Egg Nog", "base": "Brandy", "method": "Shake", "glass": "Highball", "ingredients": [ { "name": "Brandy", "qtyMl": 40 }, { "name": "Rum", "qtyMl": 20 }, { "name": "Egg Yolk", "qtyMl": 20, "label": "1 yolk" }, { "name": "Sugar Syrup", "qtyMl": 20 }, { "name": "Milk", "qtyMl": 100 }, { "name": "Cream", "qtyMl": 20 } ], "instructions": "Shake hard with ice. Strain into a glass. Dust with nutmeg." },
    { "id": "egg-sour", "name": "Egg Sour", "base": "Brandy", "method": "Shake", "glass": "Tumbler", "ingredients": [ { "name": "Brandy", "qtyMl": 40 }, { "name": "Orange Liqueur", "qtyMl": 10 }, { "name": "Lemon Juice", "qtyMl": 20 }, { "name": "Sugar Syrup", "qtyMl": 10 }, { "name": "Egg", "qtyMl": 0, "label": "1 whole" } ], "instructions": "Shake vigorously with ice. Strain into a tumbler with fresh ice. Garnish with orange slice." },
    { "id": "el-floridita", "name": "El Floridita", "base": "Rum", "method": "Shake", "glass": "Coupe", "ingredients": [ { "name": "White Rum", "qtyMl": 50 }, { "name": "Lime Juice", "qtyMl": 20 }, { "name": "Maraschino", "qtyMl": 10 }, { "name": "Grapefruit Juice", "qtyMl": 10 }, { "name": "Sugar Syrup", "qtyMl": 5 } ], "instructions": "Shake with ice. Strain into a chilled glass. (A Hemingway favorite)." },
    { "id": "el-morocco", "name": "El Morocco", "base": "Brandy", "method": "Stir", "glass": "Cocktail", "ingredients": [ { "name": "Cognac", "qtyMl": 40 }, { "name": "Cointreau", "qtyMl": 20 }, { "name": "Port", "qtyMl": 20 } ], "instructions": "Stir with ice. Strain into a chilled glass." },
    { "id": "electric-lemonade", "name": "Electric Lemonade", "base": "Vodka", "method": "Build", "glass": "Highball", "ingredients": [ { "name": "Vodka", "qtyMl": 40 }, { "name": "Blue Curaçao", "qtyMl": 20 }, { "name": "Lemon Juice", "qtyMl": 20 }, { "name": "Sugar Syrup", "qtyMl": 10 }, { "name": "Lemonade", "qtyMl": 100, "top": true } ], "instructions": "Build in a glass with ice. Top with Lemonade. Garnish with lemon." },
    { "id": "embassy", "name": "Embassy", "base": "Brandy", "method": "Shake", "glass": "Cocktail", "ingredients": [ { "name": "Brandy", "qtyMl": 30 }, { "name": "White Rum", "qtyMl": 30 }, { "name": "Cointreau", "qtyMl": 20 }, { "name": "Lime Juice", "qtyMl": 10 } ], "instructions": "Shake with ice. Strain into a chilled glass." },
    { "id": "emerald", "name": "Emerald", "base": "Gin", "method": "Stir", "glass": "Cocktail", "ingredients": [ { "name": "Gin", "qtyMl": 40 }, { "name": "Sweet Vermouth", "qtyMl": 20 }, { "name": "Blue Curaçao", "qtyMl": 10 }, { "name": "Orange Bitters", "qtyMl": 1, "label": "Dash" } ], "instructions": "Stir with ice. Strain into a chilled glass. (Also known as the 'Green' cocktail)." },
    { "id": "english-highball", "name": "English Highball", "base": "Gin", "method": "Build", "glass": "Highball", "ingredients": [ { "name": "Gin", "qtyMl": 40 }, { "name": "Brandy", "qtyMl": 20 }, { "name": "Sweet Vermouth", "qtyMl": 20 }, { "name": "Soda Water", "qtyMl": 80, "top": true } ], "instructions": "Build in a glass with ice. Top with Soda. Garnish with lemon twist." },
    { "id": "english-rose", "name": "English Rose", "base": "Gin", "method": "Shake", "glass": "Coupe", "ingredients": [ { "name": "Gin", "qtyMl": 40 }, { "name": "Dry Vermouth", "qtyMl": 20 }, { "name": "Apricot Brandy", "qtyMl": 20 }, { "name": "Lemon Juice", "qtyMl": 10 }, { "name": "Grenadine", "qtyMl": 5 } ], "instructions": "Shake with ice. Strain into a sugar-rimmed glass. Garnish with a cherry." },
    { "id": "estrellita", "name": "Estrellita", "base": "Rum", "method": "Shake", "glass": "Coupe", "ingredients": [ { "name": "White Rum", "qtyMl": 40 }, { "name": "Apricot Brandy", "qtyMl": 20 }, { "name": "Lime Juice", "qtyMl": 20 }, { "name": "Sugar Syrup", "qtyMl": 5 } ], "instructions": "Shake with ice. Strain into a chilled glass." },
    { "id": "eve", "name": "Eve", "base": "Gin", "method": "Shake", "glass": "Cocktail", "ingredients": [ { "name": "Gin", "qtyMl": 40 }, { "name": "Apricot Brandy", "qtyMl": 20 }, { "name": "Lemon Juice", "qtyMl": 20 }, { "name": "Grenadine", "qtyMl": 5 } ], "instructions": "Shake with ice. Strain into a chilled glass." },
    { "id": "eye-opener", "name": "Eye Opener", "base": "Rum", "method": "Shake", "glass": "Cocktail", "ingredients": [ { "name": "White Rum", "qtyMl": 40 }, { "name": "Egg Yolk", "qtyMl": 20, "label": "1 yolk" }, { "name": "Anisette", "qtyMl": 5 }, { "name": "Triple Sec", "qtyMl": 5 }, { "name": "Sugar Syrup", "qtyMl": 5 } ], "instructions": "Shake vigorously with ice. Strain. (Traditionally a hangover cure)." },
    { "id": "exotic", "name": "Exotic", "base": "Rum", "method": "Shake", "glass": "Highball", "ingredients": [ { "name": "White Rum", "qtyMl": 40 }, { "name": "Triple Sec", "qtyMl": 10 }, { "name": "Mango Syrup", "qtyMl": 20 }, { "name": "Pineapple Juice", "qtyMl": 60 }, { "name": "Orange Juice", "qtyMl": 40 } ], "instructions": "Shake with ice. Strain into a glass with ice. Garnish with exotic fruits." },
    { "id": "fabulous", "name": "Fabulous", "base": "Spirit", "method": "Shake", "glass": "Highball", "ingredients": [ { "name": "Grappa", "qtyMl": 30 }, { "name": "Raspberry Liqueur", "qtyMl": 20 }, { "name": "Blue Curaçao", "qtyMl": 10 }, { "name": "Orange Juice", "qtyMl": 100 } ], "instructions": "Shake with ice. Strain into a glass with ice. Garnish with orange and cherry." },
    { "id": "fallen-angel", "name": "Fallen Angel", "base": "Gin", "method": "Shake", "glass": "Cocktail", "ingredients": [ { "name": "Gin", "qtyMl": 40 }, { "name": "Lime Juice", "qtyMl": 20 }, { "name": "White Crème de Menthe", "qtyMl": 2, "label": "2 dashes" }, { "name": "Angostura Bitters", "qtyMl": 1, "label": "Dash" } ], "instructions": "Shake with ice. Strain into a chilled glass. Garnish with a cherry." },
    { "id": "fancy-brandy", "name": "Fancy Brandy", "base": "Brandy", "method": "Shake", "glass": "Cocktail", "ingredients": [ { "name": "Brandy", "qtyMl": 40 }, { "name": "Triple Sec", "qtyMl": 20 }, { "name": "Angostura Bitters", "qtyMl": 1, "label": "Dash" }, { "name": "Sugar Syrup", "qtyMl": 5 } ], "instructions": "Shake with ice. Strain into a chilled glass. Garnish with a lemon twist." },
    { "id": "fantasia", "name": "Fantasia", "base": "Rum", "method": "Shake", "glass": "Tumbler", "ingredients": [ { "name": "White Rum", "qtyMl": 30 }, { "name": "Apricot Brandy", "qtyMl": 20 }, { "name": "Pineapple Juice", "qtyMl": 20 }, { "name": "Lime Juice", "qtyMl": 10 } ], "instructions": "Shake with ice. Strain into a glass with ice. Garnish with pineapple and cherry." },
    { "id": "farmers-choice", "name": "Farmer's Choice", "base": "Calvados", "method": "Shake", "glass": "Cocktail", "ingredients": [ { "name": "Calvados", "qtyMl": 40 }, { "name": "Orange Juice", "qtyMl": 20 }, { "name": "Lime Juice", "qtyMl": 10 }, { "name": "Sugar Syrup", "qtyMl": 5 } ], "instructions": "Shake with ice. Strain into a chilled glass. Garnish with an apple slice." },
    { "id": "fernet-branca-cocktail", "name": "Fernet Branca Cocktail", "base": "Bitter", "method": "Stir", "glass": "Cocktail", "ingredients": [ { "name": "Fernet Branca", "qtyMl": 20 }, { "name": "Brandy", "qtyMl": 20 }, { "name": "Sweet Vermouth", "qtyMl": 20 } ], "instructions": "Stir with ice. Strain into a chilled glass. Garnish with a lemon twist." },
    { "id": "fifth-avenue", "name": "Fifth Avenue", "base": "Liqueur", "method": "Build", "glass": "Pousse-Café", "ingredients": [ { "name": "Crème de Cacao", "qtyMl": 20 }, { "name": "Apricot Brandy", "qtyMl": 20 }, { "name": "Cream", "qtyMl": 20 } ], "instructions": "Layer ingredients carefully in a Pousse-Café glass in the order listed." },
    { "id": "fine-and-dandy", "name": "Fine and Dandy", "base": "Gin", "method": "Shake", "glass": "Cocktail", "ingredients": [ { "name": "Gin", "qtyMl": 30 }, { "name": "Triple Sec", "qtyMl": 15 }, { "name": "Lemon Juice", "qtyMl": 15 }, { "name": "Angostura Bitters", "qtyMl": 1, "label": "Dash" } ], "instructions": "Shake with ice. Strain into a chilled glass." },
    { "id": "fino-martini", "name": "Fino Martini", "base": "Sherry", "method": "Stir", "glass": "Cocktail", "ingredients": [ { "name": "Gin", "qtyMl": 50 }, { "name": "Fino Sherry", "qtyMl": 10 } ], "instructions": "Stir with ice in a mixing glass. Strain into a chilled cocktail glass. Garnish with lemon twist." },
    { "id": "fireman-sour", "name": "Fireman Sour", "base": "Rum", "method": "Shake", "glass": "Tumbler", "ingredients": [ { "name": "White Rum", "qtyMl": 40 }, { "name": "Grenadine", "qtyMl": 20 }, { "name": "Lime Juice", "qtyMl": 30 }, { "name": "Egg White", "qtyMl": 15, "optional": true } ], "instructions": "Shake hard with ice. Strain into a glass with fresh ice. Garnish with a cherry." },
    { "id": "first-lady", "name": "First Lady", "base": "Gin", "method": "Shake", "glass": "Cocktail", "ingredients": [ { "name": "Gin", "qtyMl": 30 }, { "name": "White Crème de Cacao", "qtyMl": 20 }, { "name": "Lemon Juice", "qtyMl": 10 }, { "name": "Pineapple Juice", "qtyMl": 20 } ], "instructions": "Shake with ice. Strain into a chilled glass." },
    { "id": "five-o-clock", "name": "Five O'Clock", "base": "Rum", "method": "Stir", "glass": "Cocktail", "ingredients": [ { "name": "White Rum", "qtyMl": 40 }, { "name": "Sweet Vermouth", "qtyMl": 20 }, { "name": "Cointreau", "qtyMl": 10 }, { "name": "Lemon Juice", "qtyMl": 10 } ], "instructions": "Stir with ice. Strain into a chilled glass." },
    { "id": "flamingo", "name": "Flamingo", "base": "Gin", "method": "Shake", "glass": "Coupe", "ingredients": [ { "name": "Gin", "qtyMl": 40 }, { "name": "Apricot Brandy", "qtyMl": 20 }, { "name": "Lemon Juice", "qtyMl": 20 }, { "name": "Grenadine", "qtyMl": 5 } ], "instructions": "Shake with ice. Strain into a cocktail glass. Garnish with a cherry." },
    { "id": "florida-cocktail", "name": "Florida Cocktail", "base": "Gin", "method": "Shake", "glass": "Cocktail", "ingredients": [ { "name": "Gin", "qtyMl": 40 }, { "name": "Kirschwasser", "qtyMl": 10 }, { "name": "Cointreau", "qtyMl": 10 }, { "name": "Lemon Juice", "qtyMl": 10 }, { "name": "Orange Juice", "qtyMl": 10 } ], "instructions": "Shake with ice. Strain into a chilled glass." },
    { "id": "florida-sling", "name": "Florida Sling", "base": "Gin", "method": "Shake", "glass": "Longdrink", "ingredients": [ { "name": "Gin", "qtyMl": 40 }, { "name": "Cherry Brandy", "qtyMl": 20 }, { "name": "Lemon Juice", "qtyMl": 30 }, { "name": "Grenadine", "qtyMl": 10 }, { "name": "Pineapple Juice", "qtyMl": 60 } ], "instructions": "Shake with ice. Strain into a glass with ice. Garnish with pineapple and cherry." },
    { "id": "floridita", "name": "Floridita", "base": "Rum", "method": "Shake", "glass": "Coupe", "ingredients": [ { "name": "White Rum", "qtyMl": 50 }, { "name": "Sweet Vermouth", "qtyMl": 20 }, { "name": "White Crème de Cacao", "qtyMl": 10 }, { "name": "Grenadine", "qtyMl": 5 }, { "name": "Lime Juice", "qtyMl": 10 } ], "instructions": "Shake with ice. Strain into a chilled glass." },
    { "id": "flying", "name": "Flying", "base": "Wine/Bubbly", "method": "Shake + top", "glass": "Flute", "ingredients": [ { "name": "Gin", "qtyMl": 20 }, { "name": "Cointreau", "qtyMl": 20 }, { "name": "Lemon Juice", "qtyMl": 20 }, { "name": "Sparkling Wine", "qtyMl": 80, "top": true } ], "instructions": "Shake (except Sparkling Wine) with ice. Strain into a flute. Top with Sparkling Wine." },
    { "id": "flying-kangaroo", "name": "Flying Kangaroo", "base": "Rum", "method": "Blend", "glass": "Highball", "ingredients": [ { "name": "Vodka", "qtyMl": 20 }, { "name": "White Rum", "qtyMl": 20 }, { "name": "Galliano", "qtyMl": 20 }, { "name": "Coconut Cream", "qtyMl": 20 }, { "name": "Orange Juice", "qtyMl": 60 }, { "name": "Pineapple Juice", "qtyMl": 60 }, { "name": "Cream", "qtyMl": 20 } ], "instructions": "Blend with crushed ice. Pour into a glass." },
    { "id": "fog-cutter", "name": "Fog Cutter", "base": "Rum", "method": "Shake", "glass": "Highball", "ingredients": [ { "name": "White Rum", "qtyMl": 40 }, { "name": "Brandy", "qtyMl": 20 }, { "name": "Gin", "qtyMl": 20 }, { "name": "Lemon Juice", "qtyMl": 40 }, { "name": "Orange Juice", "qtyMl": 20 }, { "name": "Orgeat", "qtyMl": 20 }, { "name": "Sweet Sherry", "qtyMl": 10, "float": true } ], "instructions": "Shake (except Sherry) with ice. Strain into a glass with ice. Float Sherry on top." },
    { "id": "fourth-degree", "name": "Fourth Degree", "base": "Gin", "method": "Stir", "glass": "Cocktail", "ingredients": [ { "name": "Gin", "qtyMl": 30 }, { "name": "Sweet Vermouth", "qtyMl": 30 }, { "name": "Dry Vermouth", "qtyMl": 30 }, { "name": "Absinthe", "qtyMl": 1, "label": "Dash" } ], "instructions": "Stir with ice. Strain into a chilled glass." },
    { "id": "frankfurt-sour", "name": "Frankfurt Sour", "base": "Spirit", "method": "Shake", "glass": "Tumbler", "ingredients": [ { "name": "Apple Schnapps", "qtyMl": 40 }, { "name": "Lemon Juice", "qtyMl": 20 }, { "name": "Sugar Syrup", "qtyMl": 10 } ], "instructions": "Shake with ice. Strain into a glass with ice. Garnish with an apple slice." },
    { "id": "french-75", "name": "French 75", "base": "Gin", "method": "Shake + top", "glass": "Flute", "ingredients": [ { "name": "Gin", "qtyMl": 30 }, { "name": "Lemon Juice", "qtyMl": 15 }, { "name": "Sugar Syrup", "qtyMl": 15 }, { "name": "Champagne", "qtyMl": 60, "top": true } ], "instructions": "Shake (except Champagne) with ice. Strain into a flute. Top with Champagne. Garnish with lemon." },
    { "id": "french-connection", "name": "French Connection", "base": "Cognac", "method": "Build", "glass": "Tumbler", "ingredients": [ { "name": "Cognac", "qtyMl": 30 }, { "name": "Amaretto", "qtyMl": 30 } ], "instructions": "Build in a glass with ice. Stir gently." },
    { "id": "french-martini", "name": "French Martini", "base": "Vodka", "method": "Shake", "glass": "Martini", "ingredients": [ { "name": "Vodka", "qtyMl": 40 }, { "name": "Raspberry Liqueur", "qtyMl": 10 }, { "name": "Pineapple Juice", "qtyMl": 40 } ], "instructions": "Shake with ice. Strain into a chilled glass. Garnish with a lemon twist." },
    { "id": "french-sour", "name": "French Sour", "base": "Spirit", "method": "Shake", "glass": "Tumbler", "ingredients": [ { "name": "Pastis", "qtyMl": 20 }, { "name": "Apricot Brandy", "qtyMl": 20 }, { "name": "Lemon Juice", "qtyMl": 20 }, { "name": "Orange Juice", "qtyMl": 30 }, { "name": "Grenadine", "qtyMl": 10 } ], "instructions": "Shake with ice. Strain into a glass with ice. Garnish with orange and cherry." },
    { "id": "frenchy", "name": "Frenchy", "base": "Cognac", "method": "Shake", "glass": "Longdrink", "ingredients": [ { "name": "Cognac", "qtyMl": 40 }, { "name": "Crème de Bananes", "qtyMl": 20 }, { "name": "Orange Juice", "qtyMl": 60 }, { "name": "Pineapple Juice", "qtyMl": 60 }, { "name": "Strawberry Syrup", "qtyMl": 10 } ], "instructions": "Shake with ice. Strain into a glass with ice. Garnish with strawberry." },
    { "id": "frosty-night", "name": "Frosty Night", "base": "Vodka", "method": "Shake", "glass": "Cocktail", "ingredients": [ { "name": "Vodka", "qtyMl": 30 }, { "name": "Blue Curaçao", "qtyMl": 20 }, { "name": "Coconut Cream", "qtyMl": 20 }, { "name": "Pineapple Juice", "qtyMl": 40 } ], "instructions": "Shake with ice. Strain into a chilled glass." },
    { "id": "frozen-daiquiri", "name": "Frozen Daiquiri", "base": "Rum", "method": "Blend", "glass": "Coupe", "ingredients": [ { "name": "White Rum", "qtyMl": 50 }, { "name": "Lime Juice", "qtyMl": 30 }, { "name": "Sugar Syrup", "qtyMl": 10 } ], "instructions": "Blend with crushed ice until slushy. Pour into a chilled glass." },
    { "id": "frozen-margarita", "name": "Frozen Margarita", "base": "Tequila", "method": "Blend", "glass": "Coupe", "ingredients": [ { "name": "Tequila", "qtyMl": 40 }, { "name": "Triple Sec", "qtyMl": 20 }, { "name": "Lime Juice", "qtyMl": 30 } ], "instructions": "Blend with crushed ice until slushy. Pour into a salt-rimmed glass." },
    { "id": "frozen-strawberry-daiquiri", "name": "Frozen Strawberry Daiquiri", "base": "Rum", "method": "Blend", "glass": "Coupe", "ingredients": [ { "name": "White Rum", "qtyMl": 50 }, { "name": "Lime Juice", "qtyMl": 30 }, { "name": "Strawberry Liqueur", "qtyMl": 20 }, { "name": "Strawberries", "qtyMl": 0, "label": "3-5" } ], "instructions": "Blend all ingredients with crushed ice until slushy. Pour into a chilled glass." },
    { "id": "gabriella", "name": "Gabriella", "base": "Spirit", "method": "Stir", "glass": "Cocktail", "ingredients": [ { "name": "Gin", "qtyMl": 30 }, { "name": "Dry Vermouth", "qtyMl": 10 }, { "name": "Apricot Brandy", "qtyMl": 10 }, { "name": "Honey Syrup", "qtyMl": 10 } ], "instructions": "Stir with ice. Strain into a chilled glass. Garnish with a cherry." },
    { "id": "galliano-hot-shot", "name": "Galliano Hot Shot", "base": "Liqueur", "method": "Build", "glass": "Shot", "ingredients": [ { "name": "Galliano", "qtyMl": 20 }, { "name": "Hot Coffee", "qtyMl": 20, "float": true }, { "name": "Cream", "qtyMl": 20, "float": true } ], "instructions": "Layer in a shot glass: Galliano, then hot espresso, then lightly whipped cream." },
    { "id": "garibaldi", "name": "Garibaldi", "base": "Aperitif", "method": "Build", "glass": "Highball", "ingredients": [ { "name": "Campari", "qtyMl": 50 }, { "name": "Orange Juice", "qtyMl": 120 } ], "instructions": "Pour Campari into a glass with ice. Top with fluffy Orange Juice. Garnish with orange wedge." },
    { "id": "gentlemans-sour", "name": "Gentleman's Sour", "base": "Whiskey", "method": "Shake", "glass": "Tumbler", "ingredients": [ { "name": "Bourbon Whiskey", "qtyMl": 50 }, { "name": "Lemon Juice", "qtyMl": 20 }, { "name": "Orange Juice", "qtyMl": 10 }, { "name": "Sugar Syrup", "qtyMl": 10 }, { "name": "Egg White", "qtyMl": 10 } ], "instructions": "Shake hard with ice. Strain into a tumbler with fresh ice." },
    { "id": "georgia-peach", "name": "Georgia Peach", "base": "Vodka", "method": "Shake", "glass": "Highball", "ingredients": [ { "name": "Vodka", "qtyMl": 40 }, { "name": "Peach Liqueur", "qtyMl": 20 }, { "name": "Lemon Juice", "qtyMl": 10 }, { "name": "Grenadine", "qtyMl": 10 }, { "name": "Orange Juice", "qtyMl": 80 } ], "instructions": "Shake with ice. Strain into a glass with ice. Garnish with peach slice." },
    { "id": "gibson", "name": "Gibson", "base": "Gin", "method": "Stir", "glass": "Martini", "ingredients": [ { "name": "Gin", "qtyMl": 60 }, { "name": "Dry Vermouth", "qtyMl": 10 }, { "name": "Pearl Onion", "qtyMl": 0, "label": "1-2" } ], "instructions": "Stir with ice. Strain into a chilled glass. Garnish with a pearl onion (Silberzwiebel)." },
    { "id": "gillette", "name": "Gillette", "base": "Gin", "method": "Shake", "glass": "Cocktail", "ingredients": [ { "name": "Gin", "qtyMl": 40 }, { "name": "Apricot Brandy", "qtyMl": 10 }, { "name": "Dry Vermouth", "qtyMl": 10 }, { "name": "Lime Juice", "qtyMl": 10 } ], "instructions": "Shake with ice. Strain into a chilled glass." },
    { "id": "gin-and-it", "name": "Gin & It", "base": "Gin", "method": "Stir", "glass": "Cocktail", "ingredients": [ { "name": "Gin", "qtyMl": 40 }, { "name": "Sweet Vermouth", "qtyMl": 20 } ], "instructions": "Stir with ice. Strain into a chilled glass. Garnish with a cherry. ('It' stands for Italian Vermouth)." },
    { "id": "gin-and-sin", "name": "Gin & Sin", "base": "Gin", "method": "Shake", "glass": "Cocktail", "ingredients": [ { "name": "Gin", "qtyMl": 40 }, { "name": "Lemon Juice", "qtyMl": 20 }, { "name": "Orange Juice", "qtyMl": 20 }, { "name": "Grenadine", "qtyMl": 5 } ], "instructions": "Shake with ice. Strain into a chilled glass." },
    { "id": "gin-alexander", "name": "Gin Alexander", "base": "Gin", "method": "Shake", "glass": "Coupe", "ingredients": [ { "name": "Gin", "qtyMl": 30 }, { "name": "White Crème de Cacao", "qtyMl": 30 }, { "name": "Cream", "qtyMl": 30 } ], "instructions": "Shake hard with ice. Strain. Dust with nutmeg." },
    { "id": "gin-aloha", "name": "Gin Aloha", "base": "Gin", "method": "Shake", "glass": "Tumbler", "ingredients": [ { "name": "Gin", "qtyMl": 40 }, { "name": "Triple Sec", "qtyMl": 10 }, { "name": "Pineapple Juice", "qtyMl": 20 }, { "name": "Orange Juice", "qtyMl": 10 }, { "name": "Lime Juice", "qtyMl": 1, "label": "Dash" } ], "instructions": "Shake with ice. Strain into a tumbler with ice." },
    { "id": "gin-and-tonic", "name": "Gin & Tonic", "base": "Gin", "method": "Build", "glass": "Highball", "ingredients": [ { "name": "Gin", "qtyMl": 40 }, { "name": "Tonic Water", "qtyMl": 120, "top": true }, { "name": "Lemon", "qtyMl": 0, "label": "Slice" } ], "instructions": "Build in a glass with ice. Top with Tonic. Garnish with lemon or lime." },
    { "id": "gin-buck", "name": "Gin Buck", "base": "Gin", "method": "Build", "glass": "Highball", "ingredients": [ { "name": "Gin", "qtyMl": 40 }, { "name": "Lemon Juice", "qtyMl": 20 }, { "name": "Ginger Ale", "qtyMl": 100, "top": true } ], "instructions": "Build in a glass with ice. Top with Ginger Ale. Garnish with lemon slice." },
    { "id": "gin-cobbler", "name": "Gin Cobbler", "base": "Gin", "method": "Build", "glass": "Highball", "ingredients": [ { "name": "Gin", "qtyMl": 50 }, { "name": "Sugar Syrup", "qtyMl": 10 }, { "name": "Soda Water", "qtyMl": 20 }, { "name": "Pineapple", "qtyMl": 0, "label": "Pieces" }, { "name": "Orange", "qtyMl": 0, "label": "Pieces" } ], "instructions": "Dissolve sugar in soda. Add Gin and crushed ice. Decorate with fruit." },
    { "id": "gin-daisy", "name": "Gin Daisy", "base": "Gin", "method": "Shake + top", "glass": "Highball", "ingredients": [ { "name": "Gin", "qtyMl": 50 }, { "name": "Lemon Juice", "qtyMl": 20 }, { "name": "Grenadine", "qtyMl": 10 }, { "name": "Soda Water", "qtyMl": 80, "top": true } ], "instructions": "Shake (except Soda) with ice. Strain into glass with ice. Top with Soda." },
    { "id": "gin-fix", "name": "Gin Fix", "base": "Gin", "method": "Build", "glass": "Tumbler", "ingredients": [ { "name": "Gin", "qtyMl": 50 }, { "name": "Lemon Juice", "qtyMl": 20 }, { "name": "Sugar Syrup", "qtyMl": 10 }, { "name": "Water", "qtyMl": 10 } ], "instructions": "Dissolve sugar in water/lemon juice. Add Gin. Fill with crushed ice. Stir." },
    { "id": "gin-rickey", "name": "Gin Rickey", "base": "Gin", "method": "Build", "glass": "Highball", "ingredients": [ { "name": "Gin", "qtyMl": 50 }, { "name": "Lime", "qtyMl": 0, "label": "1/2" }, { "name": "Soda Water", "qtyMl": 100, "top": true } ], "instructions": "Squeeze lime into glass and drop it in. Add ice and Gin. Top with Soda." },
    { "id": "gin-sling", "name": "Gin Sling", "base": "Gin", "method": "Build", "glass": "Highball", "ingredients": [ { "name": "Gin", "qtyMl": 50 }, { "name": "Lemon Juice", "qtyMl": 20 }, { "name": "Sugar Syrup", "qtyMl": 10 }, { "name": "Water", "qtyMl": 30 } ], "instructions": "Dissolve sugar in lemon/water. Add Gin and ice. Stir." },
    { "id": "gin-sour", "name": "Gin Sour", "base": "Gin", "method": "Shake", "glass": "Tumbler", "ingredients": [ { "name": "Gin", "qtyMl": 50 }, { "name": "Lemon Juice", "qtyMl": 30 }, { "name": "Sugar Syrup", "qtyMl": 20 } ], "instructions": "Shake with ice. Strain into a tumbler with fresh ice. Garnish with cherry." },
    { "id": "gin-squirt", "name": "Gin Squirt", "base": "Gin", "method": "Shake + top", "glass": "Highball", "ingredients": [ { "name": "Gin", "qtyMl": 40 }, { "name": "Grenadine", "qtyMl": 10 }, { "name": "Pineapple Juice", "qtyMl": 20 }, { "name": "Bitter Lemon", "qtyMl": 80, "top": true }, { "name": "Soda Water", "qtyMl": 20, "top": true } ], "instructions": "Shake (except carbonated) with ice. Strain into glass. Top with Bitter Lemon and Soda." },
    { "id": "gin-swizzle", "name": "Gin Swizzle", "base": "Gin", "method": "Swizzle", "glass": "Highball", "ingredients": [ { "name": "Gin", "qtyMl": 50 }, { "name": "Lime Juice", "qtyMl": 20 }, { "name": "Sugar Syrup", "qtyMl": 10 }, { "name": "Angostura Bitters", "qtyMl": 1, "label": "Dash" }, { "name": "Soda Water", "qtyMl": 40 } ], "instructions": "Build in glass. Fill with crushed ice. 'Swizzle' (spin swizzle stick) until frosted." },
    { "id": "gipsy", "name": "Gipsy", "base": "Vodka", "method": "Stir", "glass": "Cocktail", "ingredients": [ { "name": "Vodka", "qtyMl": 40 }, { "name": "Bénédictine", "qtyMl": 20 }, { "name": "Angostura Bitters", "qtyMl": 1, "label": "Dash" } ], "instructions": "Stir with ice. Strain into a chilled glass. Garnish with lemon twist." },
    { "id": "girls-best-friend", "name": "Girl's Best Friend", "base": "Gin", "method": "Stir", "glass": "Cocktail", "ingredients": [ { "name": "Gin", "qtyMl": 30 }, { "name": "Dry Vermouth", "qtyMl": 15 }, { "name": "Sweet Vermouth", "qtyMl": 15 }, { "name": "Grand Marnier", "qtyMl": 10 } ], "instructions": "Stir with ice. Strain into a chilled glass." },
    { "id": "gloria", "name": "Gloria", "base": "Gin", "method": "Stir", "glass": "Cocktail", "ingredients": [ { "name": "Gin", "qtyMl": 40 }, { "name": "Dry Vermouth", "qtyMl": 20 }, { "name": "Campari", "qtyMl": 10 } ], "instructions": "Stir with ice. Strain into a chilled glass." },
    { "id": "gluehwein", "name": "Mulled Wine (Glühwein)", "base": "Wine/Bubbly", "method": "Build", "glass": "Mule Mug", "ingredients": [ { "name": "Red Wine", "qtyMl": 150 }, { "name": "Sugar", "qtyMl": 0, "label": "to taste" }, { "name": "Lemon", "qtyMl": 0, "label": "Zest" }, { "name": "Cloves", "qtyMl": 0, "label": "2" }, { "name": "Cinnamon Stick", "qtyMl": 0, "label": "1" } ], "instructions": "Heat ingredients together (do not boil). Remove spices. Serve hot." },
    { "id": "godfather", "name": "Godfather", "base": "Whiskey", "method": "Build", "glass": "Tumbler", "ingredients": [ { "name": "Scotch Whisky", "qtyMl": 40 }, { "name": "Amaretto", "qtyMl": 20 } ], "instructions": "Build in a tumbler over ice. Stir gently." },
    { "id": "godmother", "name": "Godmother", "base": "Vodka", "method": "Build", "glass": "Tumbler", "ingredients": [ { "name": "Vodka", "qtyMl": 40 }, { "name": "Amaretto", "qtyMl": 20 } ], "instructions": "Build in a tumbler over ice. Stir gently." },
    { "id": "golden-cadillac", "name": "Golden Cadillac", "base": "Liqueur", "method": "Shake", "glass": "Coupe", "ingredients": [ { "name": "Galliano", "qtyMl": 20 }, { "name": "White Crème de Cacao", "qtyMl": 20 }, { "name": "Cream", "qtyMl": 20 } ], "instructions": "Shake with ice. Strain into a chilled glass." },
    { "id": "golden-dream", "name": "Golden Dream", "base": "Liqueur", "method": "Shake", "glass": "Coupe", "ingredients": [ { "name": "Galliano", "qtyMl": 20 }, { "name": "Cointreau", "qtyMl": 20 }, { "name": "Orange Juice", "qtyMl": 20 }, { "name": "Cream", "qtyMl": 10 } ], "instructions": "Shake with ice. Strain into a chilled glass." },
    { "id": "golden-fizz", "name": "Golden Fizz", "base": "Gin", "method": "Shake + top", "glass": "Highball", "ingredients": [ { "name": "Gin", "qtyMl": 50 }, { "name": "Lemon Juice", "qtyMl": 30 }, { "name": "Sugar Syrup", "qtyMl": 20 }, { "name": "Egg Yolk", "qtyMl": 20, "label": "1 yolk" }, { "name": "Soda Water", "qtyMl": 80, "top": true } ], "instructions": "Shake (except Soda) vigorously with ice. Strain into glass. Top with Soda." },
    { "id": "grand-slate", "name": "Grand Slate", "base": "Gin", "method": "Stir", "glass": "Cocktail", "ingredients": [ { "name": "Gin", "qtyMl": 30 }, { "name": "Dry Vermouth", "qtyMl": 15 }, { "name": "Sweet Vermouth", "qtyMl": 15 }, { "name": "Grand Marnier", "qtyMl": 10 } ], "instructions": "Stir with ice. Strain into a chilled glass." },
    { "id": "grapefruit-cocktail", "name": "Grapefruit Cocktail", "base": "Gin", "method": "Shake", "glass": "Cocktail", "ingredients": [ { "name": "Gin", "qtyMl": 40 }, { "name": "Grapefruit Juice", "qtyMl": 20 }, { "name": "Maraschino", "qtyMl": 10 } ], "instructions": "Shake with ice. Strain into a sugar-rimmed glass." },
    { "id": "grasshopper", "name": "Grasshopper", "base": "Liqueur", "method": "Shake", "glass": "Coupe", "ingredients": [ { "name": "Green Crème de Menthe", "qtyMl": 20 }, { "name": "White Crème de Cacao", "qtyMl": 20 }, { "name": "Cream", "qtyMl": 20 } ], "instructions": "Shake with ice. Strain into a chilled glass. (Classic green dessert drink)." },
    { "id": "green-devil", "name": "Green Devil", "base": "Gin", "method": "Shake", "glass": "Cocktail", "ingredients": [ { "name": "Gin", "qtyMl": 40 }, { "name": "Green Crème de Menthe", "qtyMl": 10 }, { "name": "Lime Juice", "qtyMl": 10 } ], "instructions": "Shake with ice. Strain into a chilled glass. Garnish with a cherry." },
    { "id": "green-dragon", "name": "Green Dragon", "base": "Gin", "method": "Shake", "glass": "Cocktail", "ingredients": [ { "name": "Gin", "qtyMl": 40 }, { "name": "Green Crème de Menthe", "qtyMl": 10 }, { "name": "Kummel", "qtyMl": 10 }, { "name": "Lemon Juice", "qtyMl": 10 }, { "name": "Peach Bitters", "qtyMl": 1, "label": "Dash" } ], "instructions": "Shake with ice. Strain into a chilled glass." },
    { "id": "green-eyes", "name": "Green Eyes", "base": "Vodka", "method": "Blend", "glass": "Fancy", "ingredients": [ { "name": "Vodka", "qtyMl": 30 }, { "name": "Blue Curaçao", "qtyMl": 20 }, { "name": "Orange Juice", "qtyMl": 60 }, { "name": "Pineapple Juice", "qtyMl": 60 }, { "name": "Coconut Cream", "qtyMl": 20 } ], "instructions": "Blend with crushed ice (becomes green). Pour into a fancy glass." },
    { "id": "greyhound", "name": "Greyhound", "base": "Vodka", "method": "Build", "glass": "Highball", "ingredients": [ { "name": "Vodka", "qtyMl": 50 }, { "name": "Grapefruit Juice", "qtyMl": 120 } ], "instructions": "Build in a glass with ice. Stir." },
    { "id": "grog", "name": "Grog", "base": "Rum", "method": "Build", "glass": "Mule Mug", "ingredients": [ { "name": "Dark Rum", "qtyMl": 40 }, { "name": "Hot Water", "qtyMl": 100 }, { "name": "Sugar", "qtyMl": 10, "label": "1 tsp" } ], "instructions": "Dissolve sugar in hot water. Add Rum. Stir." },
    { "id": "gypsy-queen", "name": "Gypsy Queen", "base": "Vodka", "method": "Shake", "glass": "Cocktail", "ingredients": [ { "name": "Vodka", "qtyMl": 40 }, { "name": "Bénédictine", "qtyMl": 20 }, { "name": "Angostura Bitters", "qtyMl": 1, "label": "Dash" } ], "instructions": "Shake with ice. Strain into a chilled glass. Garnish with lemon twist." },
    { "id": "golden-slipper", "name": "Golden Slipper", "base": "Apricot", "method": "Shake", "glass": "Cocktail", "ingredients": [ { "name": "Apricot Brandy", "qtyMl": 40 }, { "name": "Yellow Chartreuse", "qtyMl": 20 }, { "name": "Egg Yolk", "qtyMl": 20, "label": "1 yolk" } ], "instructions": "Shake vigorously with ice. Strain." }
  ]
}








